code/GSIM.v
module GSIM(clk, reset, in_en, b_in, out_valid, x_out);
    input               clk;
    input               reset;
    input               in_en;
    input signed [15:0] b_in;

    output        out_valid;
    output [31:0] x_out;

    localparam RECEIVE = 0;
    localparam CALC    = 1;
    localparam SEND    = 2;

    reg signed [15:0] b   [0:15];               //store offsets b1 b2... b16 16bits each
    reg signed [31:0] ans [0:15];               //store answers x1 x2... x16 32bits each

    reg        [ 1:0] state_r, state_w;
    reg        [ 3:0] cnt_r, cnt_w;             //counter to keep track of the number of iterations
    reg        [ 2:0] cnt_stage_r, cnt_stage_w; //counter to keep track of the number of stages
    reg        [ 6:0] cnt_round_r, cnt_round_w; //counter to keep track of the number of rounds
    reg signed [39:0] w1, w2, w3, w4, w5, w6;
    reg signed [47:0] r1_r, r2_r, r3_r, r4_r, r1_w, r2_w, r3_w, r4_w;

    localparam MAX_ITER  = 15; //maximum number of variables
    localparam MAX_ROUND = 69; //maximum number of iterations
    localparam MAX_STAGE = 4;

    assign out_valid = (state_r == SEND); //output valid when in SEND state
    assign x_out     = ans[cnt_r];        //output the current answer

    function signed [47:0] mul_3;
        input signed [47:0] a;
        begin
            mul_3 = a + (a << 1);
        end
    endfunction

    function signed [47:0] mul_6;
        input signed [47:0] a;
        begin
            mul_6 = mul_3(a) << 1;
        end
    endfunction

    function signed [47:0] mul_13;
        input signed [47:0] a;
        begin
            mul_13 = a + (a << 2) + (a << 3);
        end
    endfunction

    always @(*) begin
        case (cnt_r)
            0: begin
                w1 = 0;
                w2 = 0;
                w3 = 0;
                w4 = ans[1];
                w5 = ans[2];
                w6 = ans[3];
            end
            1: begin
                w1 = ans[0];
                w2 = 0;
                w3 = 0;
                w4 = ans[2];
                w5 = ans[3];
                w6 = ans[4];
            end
            2: begin
                w1 = ans[1];
                w2 = ans[0];
                w3 = 0;
                w4 = ans[3];
                w5 = ans[4];
                w6 = ans[5];
            end
            13: begin
                w1 = ans[12];
                w2 = ans[11];
                w3 = ans[10];
                w4 = ans[14];
                w5 = ans[15];
                w6 = 0;
            end
            14: begin
                w1 = ans[13];
                w2 = ans[12];
                w3 = ans[11];
                w4 = ans[15];
                w5 = 0;
                w6 = 0;
            end
            15: begin
                w1 = ans[14];
                w2 = ans[13];
                w3 = ans[12];
                w4 = 0;
                w5 = 0;
                w6 = 0;
            end
            default: begin
                w1 = ans[cnt_r-1];
                w2 = ans[cnt_r-2];
                w3 = ans[cnt_r-3];
                w4 = ans[cnt_r+1];
                w5 = ans[cnt_r+2];
                w6 = ans[cnt_r+3];
            end
        endcase
    end

    always @(*) begin
        r1_w = r1_r;
        r2_w = r2_r;
        r3_w = r3_r;
        r4_w = r4_r;

        if (state_r == CALC) begin
            case (cnt_stage_r)
                3'd0: begin
                    r1_w = {w3, 8'd0} + {w6, 8'd0} + {{8{b[cnt_r][15]}}, b[cnt_r], 24'd0};
                    r2_w = mul_6({(w2 + w5), 8'd0});
                    r3_w = mul_13({(w1 + w4), 8'd0});
                end
                3'd1: r4_w = r1_r - r2_r + r3_r;
                3'd2: r4_w = r4_r + (r4_r >>> 4);
                3'd3: r4_w = r4_r + (r4_r >>> 8);
                3'd4: r4_w = (r4_r >>> 6) + (r4_r >>> 22) + (r4_r >>> 5) + (r4_r >>> 21);
            endcase
        end
    end

    always @(posedge clk) begin
        if (state_r == CALC) begin
            r1_r <= r1_w;
            r2_r <= r2_w;
            r3_r <= r3_w;
            r4_r <= r4_w;
            if (cnt_stage_r == MAX_STAGE) begin
                ans[cnt_r] <= r4_w[39:8];
            end
        end
    end

    always @(posedge clk) begin
        if (state_r == RECEIVE && in_en) begin
            b[cnt_r]   <= b_in;
            ans[cnt_r] <= {32'd0};
        end
    end

    //FSM
    always @(*) begin
        state_w     = state_r;
        cnt_w       = cnt_r;
        cnt_stage_w = cnt_stage_r;
        cnt_round_w = cnt_round_r;

        case (state_r)
            RECEIVE: begin
                if (in_en) begin
                    if (cnt_r == 4'd15) begin
                        state_w = CALC;
                        cnt_w   = 0;
                        cnt_stage_w = 0;
                        cnt_round_w = 0;
                    end
                    else begin
                        cnt_w = cnt_r + 1;
                    end
                end
            end

            CALC: begin
                if (cnt_stage_r == MAX_STAGE) begin
                    cnt_stage_w = 0;
                    if (cnt_r == MAX_ITER) begin
                        cnt_w = 0;
                        if (cnt_round_r == MAX_ROUND) begin
                            state_w     = SEND;
                            cnt_round_w = 0;
                        end
                        else cnt_round_w = cnt_round_r + 1;
                    end
                    else cnt_w = cnt_r + 1;
                end
                else cnt_stage_w = cnt_stage_r + 1;
            end

            SEND: begin
                if (cnt_r == 4'd15) begin
                    state_w = RECEIVE;
                    cnt_w   = 0;
                end
                else begin
                    cnt_w = cnt_r + 1;
                end
            end
        endcase
    end

    always @(posedge clk or posedge reset) begin
        if (reset) begin
            state_r     <= RECEIVE;
            cnt_stage_r <= 0;
            cnt_round_r <= 0;
            cnt_r       <= 0;
            r1_r        <= 0;
            r2_r        <= 0;
            r3_r        <= 0;
            r4_r        <= 0;
        end
        else begin
            state_r     <= state_w;
            cnt_stage_r <= cnt_stage_w;
            cnt_round_r <= cnt_round_w;
            cnt_r       <= cnt_w;
        end
    end
endmodule

code/testfixture1.v
`timescale 1ns/10ps
`define CYCLE    1           	         // Modify your clock period here
`define SDFFILE  "./Netlist/GSIM_syn.sdf"	      // Modify your sdf file name
`define PAT      "./pattern1.dat"    
module test;
parameter N_PAT   = 16;
integer k;
reg   clk ;
reg   reset ;
reg   in_en;
reg   [15:0]  b_in;
wire  out_valid;
wire  [31:0]  x_out;

reg   [15:0]  pat_mem   [0:N_PAT-1];
reg   [31:0]  x         [0:N_PAT-1];
reg   [15:0]  b         [0:N_PAT-1];
reg   [15:0]  b_tmp;
integer       loop, i, j, out_f;
reg           stop;
real  Mb [0:15];
real  x_f[0:15];
real  SquareError, error, temp;


   GSIM GSIM( .clk(clk), .reset(reset), .in_en(in_en), .b_in(b_in),
              .out_valid(out_valid), .x_out(x_out));
   

`ifdef SDF
   initial $sdf_annotate(`SDFFILE, GSIM);
`endif

initial	$readmemh (`PAT, pat_mem);


initial begin
   clk         = 1'b0;
   reset       = 1'b0;
   in_en       = 1'b0;
   b_in        = 'hz;
   stop        = 1'b0;
   loop        = 0;
end

always begin #(`CYCLE/2.0) clk = ~clk; end

initial begin
$dumpfile("GSIM.vcd");
$dumpvars;
//$fsdbDumpfile("GSIM.fsdb");
//$fsdbDumpvars;

   out_f = $fopen("out.dat");
   if (out_f == 0) begin
        $display("Output file open error !");
        $finish;
   end
end


initial begin
   @(negedge clk)    reset = 1'b1;
   #`CYCLE                reset = 1'b0;
   
   @(negedge clk)  i=0;
    while (i < N_PAT) begin               
         b_in  = pat_mem[i];
         b[i]  = pat_mem[i];
         in_en = 1'b1;
         i=i+1;                  
      @(negedge clk); 
    end     
    in_en = 1'b0;  b_in=16'hz;
end


always @(negedge clk)begin
   if(loop <16)begin
      if(out_valid)begin
         x[loop]=x_out;
         loop=loop+1;
      end
   end
   else begin
         stop=1;
   end
end


initial begin
   @(posedge stop) 
     for (j=0;j<=15;j=j+1)begin
        if(x[j][31]==1) begin   x_f[j]=~x[j] +1'b1;    x_f[j] =-x_f[j]/65536;  end
        else            begin   x_f[j]= x[j];          x_f[j] = x_f[j]/65536;  end
     end
                          
     Mb[0 ]= 20*x_f[0 ]-13*x_f[1 ]+ 6*x_f[2 ]-   x_f[3 ];
     Mb[1 ]=-13*x_f[0 ]+20*x_f[1 ]-13*x_f[2 ]+ 6*x_f[3 ]-   x_f[4 ];
     Mb[2 ]=  6*x_f[0 ]-13*x_f[1 ]+20*x_f[2 ]-13*x_f[3 ]+ 6*x_f[4 ]-  x_f[5 ];      
     Mb[3 ]=   -x_f[0 ]+ 6*x_f[1 ]-13*x_f[2 ]+20*x_f[3 ]-13*x_f[4 ]+6*x_f[5 ]-x_f[6 ];      
     Mb[4 ]=   -x_f[1 ]+ 6*x_f[2 ]-13*x_f[3 ]+20*x_f[4 ]-13*x_f[5 ]+6*x_f[6 ]-x_f[7 ];
     Mb[5 ]=   -x_f[2 ]+ 6*x_f[3 ]-13*x_f[4 ]+20*x_f[5 ]-13*x_f[6 ]+6*x_f[7 ]-x_f[8 ];                    
     Mb[6 ]=   -x_f[3 ]+ 6*x_f[4 ]-13*x_f[5 ]+20*x_f[6 ]-13*x_f[7 ]+6*x_f[8 ]-x_f[9 ];
     Mb[7 ]=   -x_f[4 ]+ 6*x_f[5 ]-13*x_f[6 ]+20*x_f[7 ]-13*x_f[8 ]+6*x_f[9 ]-x_f[10];
     Mb[8 ]=   -x_f[5 ]+ 6*x_f[6 ]-13*x_f[7 ]+20*x_f[8 ]-13*x_f[9 ]+6*x_f[10]-x_f[11];
     Mb[9 ]=   -x_f[6 ]+ 6*x_f[7 ]-13*x_f[8 ]+20*x_f[9 ]-13*x_f[10]+6*x_f[11]-x_f[12];
     Mb[10]=   -x_f[7 ]+ 6*x_f[8 ]-13*x_f[9 ]+20*x_f[10]-13*x_f[11]+6*x_f[12]-x_f[13];
     Mb[11]=   -x_f[8 ]+ 6*x_f[9 ]-13*x_f[10]+20*x_f[11]-13*x_f[12]+6*x_f[13]-x_f[14];
     Mb[12]=   -x_f[9 ]+ 6*x_f[10]-13*x_f[11]+20*x_f[12]-13*x_f[13]+6*x_f[14]-x_f[15];     
     Mb[13]=   -x_f[10]+ 6*x_f[11]-13*x_f[12]+20*x_f[13]-13*x_f[14]+6*x_f[15];
     Mb[14]=   -x_f[11]+ 6*x_f[12]-13*x_f[13]+20*x_f[14]-13*x_f[15];
     Mb[15]=   -x_f[12]+ 6*x_f[13]-13*x_f[14]+20*x_f[15];   
        
     SquareError = 0;        
     
     for(j=0; j<=15; j=j+1)begin     	  
       	if(b[j][15]==1)begin 
       		b_tmp= ~b[j]+1;
       		temp = b_tmp;
       		error= temp + Mb[j];
       	end
       	else begin
       		error = Mb[j] - b[j];
       	end
       	//$display(" Loop=%d    error= %.15f  \n", j, error);
     	  SquareError = SquareError + error*error;
     end
                   
     $display("-----------------------------------------------------\n");
     $display("            Your Output              Golden X\n");
     $display("  X1:     %.10f            402.1120217501   \n", x_f[0 ]);
     $display("  X2:     %.10f           1689.5336804421   \n", x_f[1 ]);
     $display("  X3:     %.10f           2455.4774264763   \n", x_f[2 ]);
     $display("  X4:     %.10f            563.1671481130   \n", x_f[3 ]);
     $display("  X5:     %.10f            703.0136705772   \n", x_f[4 ]);
     $display("  X6:     %.10f           1745.1919122734   \n", x_f[5 ]);
     $display("  X7:     %.10f             33.2002351074   \n", x_f[6 ]);
     $display("  X8:     %.10f            607.1379155812   \n", x_f[7 ]);
     $display("  X9:     %.10f           -477.5895727426   \n", x_f[8 ]);
     $display(" X10:     %.10f            869.0943789319   \n", x_f[9 ]);
     $display(" X11:     %.10f           1907.5237775384   \n", x_f[10]);
     $display(" X12:     %.10f           1524.3408800767   \n", x_f[11]);
     $display(" X13:     %.10f            596.4154551345   \n", x_f[12]);
     $display(" X14:     %.10f           1476.6345624265   \n", x_f[13]);
     $display(" X15:     %.10f           1011.5707976786   \n", x_f[14]);
     $display(" X16:     %.10f          -1330.8985774801   \n", x_f[15]);          
     $display("-----------------------------------------------------\n");
     $display("So Your Error Ratio=  %.15f\n", SquareError);
     $display("-----------------------------------------------------\n");   
     
     error=SquareError;
     if(error<0.000001 && error!='hx && error!='hz)begin                           
         $display("Your Score Level: A \n");  
         $display("Congratulations! GSIM's Function Successfully!\n");
         $display("-------------------------PASS------------------------\n");
     end    
         
     else if(error>=0.000001 && error <0.000005 && error!='hx && error!='hz)begin
        $display("Your Score Level: B \n");
        $display("Congratulations! GSIM's Function Successfully!\n");
        $display("-------------------------PASS------------------------\n");
     end
     else if(error>=0.000005 && error <0.000010 && error!='hx && error!='hz)begin
        $display("Your Score Level: C \n");
        $display("Congratulations! GSIM's Function Successfully!\n");
        $display("-------------------------PASS------------------------\n");
     end 
     else if(error>=0.000010 && error <0.000050 && error!='hx && error!='hz)begin
        $display("Your Score Level: D \n");
        $display("Congratulations! GSIM's Function Successfully!\n");
        $display("-------------------------PASS------------------------\n");
     end 
        
     else if(error>=0.000050 && error <0.000100 && error!='hx && error!='hz)begin
        $display("Your Score Level: E \n");
        $display("Congratulations! GSIM's Function Successfully!\n");
        $display("-------------------------PASS------------------------\n");
     end     
     else if(error>=0.000100 && error <0.001000 && error!='hx && error!='hz)begin
        $display("Your Score Level: F \n");
        $display("Congratulations! GSIM's Function Successfully!\n");
        $display("-------------------------PASS------------------------\n");
     end 
     else if(error>=0.001000 && error <0.005000 && error!='hx && error!='hz)begin
        $display("Your Score Level: G \n");
        $display("Congratulations! GSIM's Function Successfully!\n");
        $display("-------------------------PASS------------------------\n");
     end 
     else if(error>=0.005000 && error <0.010000 && error!='hx && error!='hz)begin
        $display("Your Score Level: H \n");
        $display("Congratulations! GSIM's Function Successfully!\n");
        $display("-------------------------PASS------------------------\n");
     end 
     else if(error>=0.010000 && error <0.100000 && error!='hx && error!='hz)begin
        $display("Your Score Level: I \n");
        $display("Congratulations! GSIM's Function Successfully!\n");
        $display("-------------------------PASS------------------------\n");
     end 
     else if(error>=0.100000 && error <0.300000 && error!='hx && error!='hz)begin
        $display("Your Score Level: J \n");
        $display("Congratulations! GSIM's Function Successfully!\n");
        $display("-------------------------PASS------------------------\n");
     end 
     else begin
        $display("Your Score Level: K \n");                  
        $display("-------------   GSIM's Function Fail   -------------\n");
        $display("-------------------------Fail------------------------\n");
     end
      
      #(`CYCLE/2); $finish;
                       
end
   
endmodule

code/GSIM.vcd
$date
	Thu May  1 01:37:24 2025
$end
$version
	Icarus Verilog
$end
$timescale
	10ps
$end
$scope module test $end
$var wire 32 ! x_out [31:0] $end
$var wire 1 " out_valid $end
$var reg 16 # b_in [15:0] $end
$var reg 16 $ b_tmp [15:0] $end
$var reg 1 % clk $end
$var reg 1 & in_en $end
$var reg 1 ' reset $end
$var reg 1 ( stop $end
$var real 1 ) SquareError $end
$var real 1 * error $end
$var integer 32 + i [31:0] $end
$var integer 32 , j [31:0] $end
$var integer 32 - loop [31:0] $end
$var integer 32 . out_f [31:0] $end
$var real 1 / temp $end
$scope module GSIM $end
$var wire 16 0 b_in [15:0] $end
$var wire 1 % clk $end
$var wire 1 & in_en $end
$var wire 1 ' reset $end
$var wire 32 1 x_out [31:0] $end
$var wire 1 " out_valid $end
$var reg 4 2 cnt_r [3:0] $end
$var reg 7 3 cnt_round_r [6:0] $end
$var reg 7 4 cnt_round_w [6:0] $end
$var reg 3 5 cnt_stage_r [2:0] $end
$var reg 3 6 cnt_stage_w [2:0] $end
$var reg 4 7 cnt_w [3:0] $end
$var reg 48 8 r1_r [47:0] $end
$var reg 48 9 r1_w [47:0] $end
$var reg 48 : r2_r [47:0] $end
$var reg 48 ; r2_w [47:0] $end
$var reg 48 < r3_r [47:0] $end
$var reg 48 = r3_w [47:0] $end
$var reg 48 > r4_r [47:0] $end
$var reg 48 ? r4_w [47:0] $end
$var reg 2 @ state_r [1:0] $end
$var reg 2 A state_w [1:0] $end
$var reg 40 B w1 [39:0] $end
$var reg 40 C w2 [39:0] $end
$var reg 40 D w3 [39:0] $end
$var reg 40 E w4 [39:0] $end
$var reg 40 F w5 [39:0] $end
$var reg 40 G w6 [39:0] $end
$scope function mul_13 $end
$var reg 48 H a [47:0] $end
$upscope $end
$scope function mul_3 $end
$var reg 48 I a [47:0] $end
$upscope $end
$scope function mul_6 $end
$var reg 48 J a [47:0] $end
$upscope $end
$upscope $end
$upscope $end
$enddefinitions $end
#0
$dumpvars
bx J
bx I
bx H
bx G
bx F
bx E
bx D
bx C
bx B
bx A
bx @
bx ?
bx >
bx =
bx <
bx ;
bx :
bx 9
bx 8
bx 7
bx 6
bx 5
bx 4
bx 3
bx 2
bx 1
bz 0
r0 /
b10 .
b0 -
bx ,
bx +
r0 *
r0 )
0(
0'
0&
0%
bx $
bz #
x"
bx !
$end
#500
1%
#1000
b0 D
b0 C
b0 B
b0 4
b0 6
b0 7
b0 A
b0 ?
b0 =
b0 ;
b0 9
b0 2
b0 3
b0 5
0"
b0 @
b0 >
b0 <
b0 :
b0 8
1'
0%
#1500
1%
#2000
b1 7
1&
b101011110001000 #
b101011110001000 0
b1 +
0%
0'
#2500
b10 7
b1 2
bx !
bx 1
1%
#3000
b10 +
b101010100111010 #
b101010100111010 0
0%
#3500
b11 7
b10 2
1%
#4000
b11 +
b1100000110100110 #
b1100000110100110 0
0%
#4500
b100 7
b11 2
bx !
bx 1
1%
#5000
b100 +
b1110100001100 #
b1110100001100 0
0%
#5500
b101 7
b100 2
1%
#6000
b101 +
b1010100001110 #
b1010100001110 0
0%
#6500
b110 7
b101 2
bx !
bx 1
1%
#7000
b110 +
b101001101110 #
b101001101110 0
0%
#7500
b111 7
b110 2
1%
#8000
b111 +
b101111010110100 #
b101111010110100 0
0%
#8500
b1000 7
b111 2
bx !
bx 1
1%
#9000
b1000 +
b1100001111001001 #
b1100001111001001 0
0%
#9500
b1001 7
b1000 2
1%
#10000
b1001 +
b1101000101101101 #
b1101000101101101 0
0%
#10500
b1010 7
b1001 2
bx !
bx 1
1%
#11000
b1010 +
b1001111010000101 #
b1001111010000101 0
0%
#11500
b1011 7
b1010 2
1%
#12000
b1011 +
b111000010011000 #
b111000010011000 0
0%
#12500
b1100 7
b1011 2
bx !
bx 1
1%
#13000
b1100 +
b10010101000011 #
b10010101000011 0
0%
#13500
b1101 7
b1100 2
1%
#14000
b1101 +
b1111101010111110 #
b1111101010111110 0
0%
#14500
b1110 7
b0 G
b1101 2
bx !
bx 1
1%
#15000
b1110 +
b10001110101010 #
b10001110101010 0
0%
#15500
b1111 7
b0 F
b1110 2
1%
#16000
b1111 +
b101101110010 #
b101101110010 0
0%
#16500
b0 7
b1 A
b0 E
b1111 2
bx !
bx 1
1%
#17000
b10000 +
b10010110110110 #
b10010110110110 0
0%
#17500
b1 6
b0 H
b0 I
b0 J
b101011110001000000000000000000000000000 9
b0 !
b0 1
b0 2
b1 @
1%
#18000
b1 6
bz #
bz 0
0&
0%
#18500
b10 6
b101011110001000000000000000000000000000 ?
b1 5
b101011110001000000000000000000000000000 8
1%
#19000
0%
#19500
b11 6
b101110100000000100000000000000000000000 ?
b101011110001000000000000000000000000000 >
b10 5
1%
#20000
0%
#20500
b100 6
b101110101011101100000001000000000000000 ?
b11 5
b101110100000000100000000000000000000000 >
1%
#21000
0%
#21500
b1 7
b0 6
b10001100000011001100110011001100010 ?
b101110101011101100000001000000000000000 >
b100 5
1%
#22000
0%
#22500
b11100011100101001100110010111000000000 =
b10001100000011001100110011000000000 H
b1 6
b100011000000110011001100110 B
b101010100111010000000000000000000000000 9
b1 2
b0 5
b0 !
b0 1
b10001100000011001100110011001100010 >
1%
#23000
0%
#23500
b10 6
b1000111000011111001100110010111000000000 ?
b11100011100101001100110010111000000000 <
b101010100111010000000000000000000000000 8
b1 5
1%
#24000
0%
#24500
b11 6
b1001011100000001001001100110000011100000 ?
b10 5
b1000111000011111001100110010111000000000 >
1%
#25000
0%
#25500
b100 6
b1001011110011000001001111000011101000000 ?
b1001011100000001001001100110000011100000 >
b11 5
1%
#26000
0%
#26500
b10 7
b0 6
b11100011011001010001111010101111000 ?
b100 5
b1001011110011000001001111000011101000000 >
1%
#27000
0%
#27500
b101110001100001000101000111000100000000 =
b11100011011001010001111010100000000 H
b1101001000010011001100110010000000000 ;
b10001100000011001100110011000000000 I
b10001100000011001100110011000000000 J
b100011000000110011001100110 C
b111000110110010100011110101 B
b1 6
b111111111100000110100110000000000000000000000000 9
b11100011011001010001111010101111000 >
b10 2
b0 5
1%
#28000
0%
#28500
b10 6
b1111000100101011100000110100000000 ?
b1 5
b101110001100001000101000111000100000000 <
b1101001000010011001100110010000000000 :
b111111111100000110100110000000000000000000000000 8
1%
#29000
0%
#29500
b11 6
b10000000000111110001110110111010000 ?
b1111000100101011100000110100000000 >
b10 5
1%
#30000
0%
#30500
b100 6
b10000000100111110011110011010111101 ?
b11 5
b10000000000111110001110110111010000 >
1%
#31000
0%
#31500
b11 7
b0 6
b110000001110111110011100001001 ?
b10000000100111110011110011010111101 >
b100 5
1%
#32000
0%
#32500
b1001110011000010101011101100000000 =
b110000001110111110011100000000 H
b10101010100010111101011011111000000000 ;
b11100011011001010001111010100000000 I
b11100011011001010001111010100000000 J
b1 6
b100011000000110011001100110 D
b111000110110010100011110101 C
b1100000011101111100111 B
b10000101101100011001100110011000000000 9
b11 2
b0 5
b0 !
b0 1
b110000001110111110011100001001 >
1%
#33000
0%
#33500
b10 6
b111111111111100100111100011110110110001100000000 ?
b1001110011000010101011101100000000 <
b10101010100010111101011011111000000000 :
b10000101101100011001100110011000000000 8
b1 5
1%
#34000
0%
#34500
b11 6
b111111111111100011010000010000110001100100110000 ?
b10 5
b111111111111100100111100011110110110001100000000 >
1%
#35000
0%
#35500
b100 6
b111111111111100011001001000100110101110001001001 ?
b111111111111100011010000010000110001100100110000 >
b11 5
1%
#36000
0%
#36500
b100 7
b0 6
b111111111111111110101001011011001001000110111111 ?
b100 5
b111111111111100011001001000100110101110001001001 >
1%
#37000
0%
#37500
b111111111111101110011010100000110101110100000000 =
b111111111111111110101001011011001001000100000000 H
b100100001011001110110101000000000 ;
b110000001110111110011100000000 I
b110000001110111110011100000000 J
b111000110110010100011110101 D
b1100000011101111100111 C
b1111111111111111101010010110110010010001 B
b1 6
b1110000101001001010001111010100000000 9
b111111111111111110101001011011001001000110111111 >
b100 2
b0 5
1%
#38000
0%
#38500
b10 6
b1011010100010010001001110100000000000 ?
b1 5
b111111111111101110011010100000110101110100000000 <
b100100001011001110110101000000000 :
b1110000101001001010001111010100000000 8
1%
#39000
0%
#39500
b11 6
b1100000001100011010010011011010000000 ?
b1011010100010010001001110100000000000 >
b10 5
1%
#40000
0%
#40500
b100 6
b1100000100100011101011001111110110110 ?
b11 5
b1100000001100011010010011011010000000 >
1%
#41000
0%
#41500
b101 7
b0 6
b100100001101101101010010100101111 ?
b1100000100100011101011001111110110110 >
b100 5
1%
#42000
0%
#42500
b111010110110010001100110000100000000 =
b100100001101101101010010100000000 H
b111111111111110111111000100010110110011000000000 ;
b111111111111111110101001011011001001000100000000 I
b111111111111111110101001011011001001000100000000 J
b1 6
b1100000011101111100111 D
b1111111111111111101010010110110010010001 C
b1001000011011011010100101 B
b101010011110001110111110011100000000 9
b101 2
b0 5
b0 !
b0 1
b100100001101101101010010100101111 >
1%
#43000
0%
#43500
b10 6
b1101101011011111101101110001000000000 ?
b111010110110010001100110000100000000 <
b111111111111110111111000100010110110011000000000 :
b101010011110001110111110011100000000 8
b1 5
1%
#44000
0%
#44500
b11 6
b1110100010001101101100101000000100000 ?
b10 5
b1101101011011111101101110001000000000 >
1%
#45000
0%
#45500
b100 6
b1110100101110110010000000011001110000 ?
b1110100010001101101100101000000100000 >
b11 5
1%
#46000
0%
#46500
b110 7
b0 6
b101011110001100101011111001111101 ?
b100 5
b1110100101110110010000000011001110000 >
1%
#47000
0%
#47500
b1000111001000100100111010011000000000 =
b101011110001100101011111000000000 H
b11011001010010001111101111000000000 ;
b100100001101101101010010100000000 I
b100100001101101101010010100000000 J
b1111111111111111101010010110110010010001 D
b1001000011011011010100101 C
b1010111100011001010111110 B
b1 6
b101111001011101011011001001000100000000 9
b101011110001100101011111001111101 >
b110 2
b0 5
1%
#48000
0%
#48500
b10 6
b110100101011011101110000101100100000000 ?
b1 5
b1000111001000100100111010011000000000 <
b11011001010010001111101111000000000 :
b101111001011101011011001001000100000000 8
1%
#49000
0%
#49500
b11 6
b110111111110001011100111101111010010000 ?
b110100101011011101110000101100100000000 >
b10 5
1%
#50000
0%
#50500
b100 6
b111000001100001011001010101001001101110 ?
b11 5
b110111111110001011100111101111010010000 >
1%
#51000
0%
#51500
b111 7
b0 6
b10101000100100101100000010001101100 ?
b111000001100001011001010101001001101110 >
b100 5
1%
#52000
0%
#52500
b100010001111011100111100011010000000000 =
b10101000100100101100000010000000000 H
b100000110101001100000111010000000000 ;
b101011110001100101011111000000000 I
b101011110001100101011111000000000 J
b1 6
b1001000011011011010100101 D
b1010111100011001010111110 C
b101010001001001011000000100 B
b111111111100010011101010101101101010010100000000 9
b111 2
b0 5
b0 !
b0 1
b10101000100100101100000010001101100 >
1%
#53000
0%
#53500
b10 6
b100110001001001000110010100000000 ?
b100010001111011100111100011010000000000 <
b100000110101001100000111010000000000 :
b111111111100010011101010101101101010010100000000 8
b1 5
1%
#54000
0%
#54500
b11 6
b101000100001101101010101101010000 ?
b10 5
b100110001001001000110010100000000 >
1%
#55000
0%
#55500
b100 6
b101000101011110101110000111111011 ?
b101000100001101101010101101010000 >
b11 5
1%
#56000
0%
#56500
b1000 7
b0 6
b1111010000011101000111010110 ?
b100 5
b101000101011110101110000111111011 >
1%
#57000
0%
#57500
b11000110010101111001110100000000 =
b1111010000011101000100000000 H
b1111110011011100001000001100000000000 ;
b10101000100100101100000010000000000 I
b10101000100100101100000010000000000 J
b1010111100011001010111110 D
b101010001001001011000000100 C
b11110100000111010001 B
b1 6
b111111111101001011001011001100101011111000000000 9
b1111010000011101000111010110 >
b1000 2
b0 5
1%
#58000
0%
#58500
b10 6
b111111111011001111110110000001100100001100000000 ?
b1 5
b11000110010101111001110100000000 <
b1111110011011100001000001100000000000 :
b111111111101001011001011001100101011111000000000 8
1%
#59000
0%
#59500
b11 6
b111111111010111100110101011001101010011100110000 ?
b111111111011001111110110000001100100001100000000 >
b10 5
1%
#60000
0%
#60500
b100 6
b111111111010111011100100100111000000110111010111 ?
b11 5
b111111111010111100110101011001101010011100110000 >
1%
#61000
0%
#61500
b1001 7
b0 6
b111111111111110000110010101100111000001101011011 ?
b111111111010111011100100100111000000110111010111 >
b100 5
1%
#62000
0%
#62500
b111111111100111010010011000111011010011100000000 =
b111111111111110000110010101100111000001100000000 H
b1011011100010101110011000000000 ;
b1111010000011101000100000000 I
b1111010000011101000100000000 J
b1 6
b101010001001001011000000100 D
b11110100000111010001 C
b1111111111111100001100101011001110000011 B
b111111111010001111001001100101100000010000000000 9
b1001 2
b0 5
b0 !
b0 1
b111111111111110000110010101100111000001101011011 >
1%
#63000
0%
#63500
b10 6
b111111110111001000000001001010001100010100000000 ?
b111111111100111010010011000111011010011100000000 <
b1011011100010101110011000000000 :
b111111111010001111001001100101100000010000000000 8
b1 5
1%
#64000
0%
#64500
b11 6
b111111110110100100100001001110110101000101010000 ?
b10 5
b111111110111001000000001001010001100010100000000 >
1%
#65000
0%
#65500
b100 6
b111111110110100010001010010111001000110010100001 ?
b111111110110100100100001001110110101000101010000 >
b11 5
1%
#66000
0%
#66500
b1010 7
b0 6
b111111111111100011100110011101010011110100010010 ?
b100 5
b111111110110100010001010010111001000110010100001 >
1%
#67000
0%
#67500
b111111111010001110110011111101000001100100000000 =
b111111111111100011100110011101010011110100000000 H
b111111111110100100110000001101010001001000000000 ;
b111111111111110000110010101100111000001100000000 I
b111111111111110000110010101100111000001100000000 J
b11110100000111010001 D
b1111111111111100001100101011001110000011 C
b1111111111111000111001100111010100111101 B
b1 6
b111000010100111010000011101000100000000 9
b111111111111100011100110011101010011110100010010 >
b1010 2
b0 5
1%
#68000
0%
#68500
b10 6
b10101100101011000000001101100000000000 ?
b1 5
b111111111010001110110011111101000001100100000000 <
b111111111110100100110000001101010001001000000000 :
b111000010100111010000011101000100000000 8
1%
#69000
0%
#69500
b11 6
b10110111011101101100001110010110000000 ?
b10101100101011000000001101100000000000 >
b10 5
1%
#70000
0%
#70500
b100 6
b10111000001011100011101001011001100101 ?
b11 5
b10110111011101101100001110010110000000 >
1%
#71000
0%
#71500
b1011 7
b0 6
b1000101000100011001101011110010110 ?
b10111000001011100011101001011001100101 >
b100 5
1%
#72000
0%
#72500
b1110000001111001001101110101100000000 =
b1000101000100011001101011100000000 H
b111111111101010101100110101111110110111000000000 ;
b111111111111100011100110011101010011110100000000 I
b111111111111100011100110011101010011110100000000 J
b1 6
b1111111111111100001100101011001110000011 D
b1111111111111000111001100111010100111101 C
b10001010001000110011010111 B
b10000101110101101100111000001100000000 9
b1011 2
b0 5
b0 !
b0 1
b1000101000100011001101011110010110 >
1%
#73000
0%
#73500
b10 6
b110100000011110000110110000000000000000 ?
b1110000001111001001101110101100000000 <
b111111111101010101100110101111110110111000000000 :
b10000101110101101100111000001100000000 8
b1 5
1%
#74000
0%
#74500
b11 6
b110111010011111111111001011000000000000 ?
b10 5
b110100000011110000110110000000000000000 >
1%
#75000
0%
#75500
b100 6
b110111100001110100111001010110010110000 ?
b110111010011111111111001011000000000000 >
b11 5
1%
#76000
0%
#76500
b1100 7
b0 6
b10100110100101101001000110011000101 ?
b100 5
b110111100001110100111001010110010110000 >
1%
#77000
0%
#77500
b100001110101101001010110001110000000000 =
b10100110100101101001000110000000000 H
b110011110011010011010000101000000000 ;
b1000101000100011001101011100000000 I
b1000101000100011001101011100000000 J
b1111111111111000111001100111010100111101 D
b10001010001000110011010111 C
b101001101001011010010001100 B
b1 6
b111111111111001110100100011101010011110100000000 9
b10100110100101101001000110011000101 >
b1100 2
b0 5
1%
#78000
0%
#78500
b10 6
b10101001011110010100110100111100000000 ?
b1 5
b100001110101101001010110001110000000000 <
b110011110011010011010000101000000000 :
b111111111111001110100100011101010011110100000000 8
1%
#79000
0%
#79500
b11 6
b10110100000100001110001000001111110000 ?
b10101001011110010100110100111100000000 >
b10 5
1%
#80000
0%
#80500
b100 6
b10110100110001001111001011110001110011 ?
b11 5
b10110100000100001110001000001111110000 >
1%
#81000
0%
#81500
b1101 7
b0 6
b1000011110010100001111011100100001 ?
b10110100110001001111001011110001110011 >
b100 5
1%
#82000
0%
