code/GSIM.v
module GSIM(clk, reset, in_en, b_in, out_valid, x_out);
    input               clk;
    input               reset;
    input               in_en;
    input signed [15:0] b_in;

    output        out_valid;
    output [31:0] x_out;

    localparam RECEIVE = 0;
    localparam CALC    = 1;
    localparam SEND    = 2;

    reg signed [15:0] b   [0:15];               //store offsets b1 b2... b16 16bits each
    reg signed [39:0] ans [0:15];               //store answers x1 x2... x16 32bits each

    reg        [ 1:0] state_r, state_w;
    reg        [ 3:0] cnt_r, cnt_w;             //counter to keep track of the number of iterations
    reg        [ 2:0] cnt_stage_r, cnt_stage_w; //counter to keep track of the number of stages
    reg        [ 6:0] cnt_round_r, cnt_round_w; //counter to keep track of the number of rounds
    reg signed [39:0] w1, w2, w3, w4, w5, w6;
    reg signed [39:0] r1_r, r2_r, r3_r, r4_r, r1_w, r2_w, r3_w, r4_w;

    localparam MAX_ITER  = 15; //maximum number of variables
    localparam MAX_ROUND = 99; //maximum number of iterations
    localparam MAX_STAGE = 4;

    assign out_valid = (state_r == SEND); //output valid when in SEND state
    assign x_out     = ans[cnt_r];        //output the current answer

    function signed [39:0] mul_3;
        input signed [39:0] a;
        begin
            mul_3 = a + (a << 1);
        end
    endfunction

    function signed [39:0] mul_6;
        input signed [39:0] a;
        begin
            mul_6 = mul_3(a) << 1;
        end
    endfunction

    function signed [39:0] mul_13;
        input signed [39:0] a;
        begin
            mul_13 = a + (a << 2) + (a << 3);
        end
    endfunction

    always @(*) begin
        case (cnt_r)
            0: begin
                w1 = 0;
                w2 = 0;
                w3 = 0;
                w4 = ans[1];
                w5 = ans[2];
                w6 = ans[3];
            end
            1: begin
                w1 = ans[0];
                w2 = 0;
                w3 = 0;
                w4 = ans[2];
                w5 = ans[3];
                w6 = ans[4];
            end
            2: begin
                w1 = ans[1];
                w2 = ans[0];
                w3 = 0;
                w4 = ans[3];
                w5 = ans[4];
                w6 = ans[5];
            end
            13: begin
                w1 = ans[12];
                w2 = ans[11];
                w3 = ans[10];
                w4 = ans[14];
                w5 = ans[15];
                w6 = 0;
            end
            14: begin
                w1 = ans[13];
                w2 = ans[12];
                w3 = ans[11];
                w4 = ans[15];
                w5 = 0;
                w6 = 0;
            end
            15: begin
                w1 = ans[14];
                w2 = ans[13];
                w3 = ans[12];
                w4 = 0;
                w5 = 0;
                w6 = 0;
            end
            default: begin
                w1 = ans[cnt_r-1];
                w2 = ans[cnt_r-2];
                w3 = ans[cnt_r-3];
                w4 = ans[cnt_r+1];
                w5 = ans[cnt_r+2];
                w6 = ans[cnt_r+3];
            end
        endcase
    end

    always @(*) begin
        r1_w = r1_r;
        r2_w = r2_r;
        r3_w = r3_r;
        r4_w = r4_r;

        if (state_r == CALC) begin
            case (cnt_stage_r)
                3'd0: begin
                    r1_w = w3 + w6 + {{8{b[cnt_r][15]}}, b[cnt_r], 16'd0};
                    r2_w = mul_6((w2 + w5));
                    r3_w = mul_13((w1 + w4));
                end
                3'd1: r4_w = r1_r - r2_r + r3_r;
                3'd2: r4_w = r4_r + (r4_r >>> 4);
                3'd3: r4_w = r4_r + (r4_r >>> 8);
                3'd4: r4_w = (r4_r >>> 6) + (r4_r >>> 22) + (r4_r >>> 5) + (r4_r >>> 21);
            endcase
        end
    end

    always @(posedge clk) begin
        if (state_r == CALC) begin
            r1_r <= r1_w;
            r2_r <= r2_w;
            r3_r <= r3_w;
            r4_r <= r4_w;
            if (cnt_stage_r == MAX_STAGE) begin
                ans[cnt_r] <= r4_w;
            end
        end
    end

    always @(posedge clk) begin
        if (state_r == RECEIVE && in_en) begin
            b[cnt_r]   <= b_in;
            ans[cnt_r] <= {40'd0};
        end
    end

    //FSM
    always @(*) begin
        state_w     = state_r;
        cnt_w       = cnt_r;
        cnt_stage_w = cnt_stage_r;
        cnt_round_w = cnt_round_r;

        case (state_r)
            RECEIVE: begin
                if (in_en) begin
                    if (cnt_r == 4'd15) begin
                        state_w = CALC;
                        cnt_w   = 0;
                        cnt_stage_w = 0;
                        cnt_round_w = 0;
                    end
                    else begin
                        cnt_w = cnt_r + 1;
                    end
                end
            end

            CALC: begin
                if (cnt_stage_r == MAX_STAGE) begin
                    cnt_stage_w = 0;
                    if (cnt_r == MAX_ITER) begin
                        cnt_w = 0;
                        if (cnt_round_r == MAX_ROUND) begin
                            state_w     = SEND;
                            cnt_round_w = 0;
                        end
                        else cnt_round_w = cnt_round_r + 1;
                    end
                    else cnt_w = cnt_r + 1;
                end
                else cnt_stage_w = cnt_stage_r + 1;
            end

            SEND: begin
                if (cnt_r == 4'd15) begin
                    state_w = RECEIVE;
                    cnt_w   = 0;
                end
                else begin
                    cnt_w = cnt_r + 1;
                end
            end
        endcase
    end

    always @(posedge clk or posedge reset) begin
        if (reset) begin
            state_r     <= RECEIVE;
            cnt_stage_r <= 0;
            cnt_round_r <= 0;
            cnt_r       <= 0;
            r1_r        <= 0;
            r2_r        <= 0;
            r3_r        <= 0;
            r4_r        <= 0;
        end
        else begin
            state_r     <= state_w;
            cnt_stage_r <= cnt_stage_w;
            cnt_round_r <= cnt_round_w;
            cnt_r       <= cnt_w;
        end
    end
endmodule

code/testfixture1.v
`timescale 1ns/10ps
`define CYCLE    10.0           	         // Modify your clock period here
`define SDFFILE  "./GSIM_syn.sdf"	      // Modify your sdf file name
`define PAT      "./pattern1.dat"    
module test;
parameter N_PAT   = 16;
integer k;
reg   clk ;
reg   reset ;
reg   in_en;
reg   [15:0]  b_in;
wire  out_valid;
wire  [31:0]  x_out;

reg   [15:0]  pat_mem   [0:N_PAT-1];
reg   [31:0]  x         [0:N_PAT-1];
reg   [15:0]  b         [0:N_PAT-1];
reg   [15:0]  b_tmp;
integer       loop, i, j, out_f;
reg           stop;
real  Mb [0:15];
real  x_f[0:15];
real  SquareError, error, temp;


   GSIM GSIM( .clk(clk), .reset(reset), .in_en(in_en), .b_in(b_in),
              .out_valid(out_valid), .x_out(x_out));
   

`ifdef SDF
   initial $sdf_annotate(`SDFFILE, GSIM);
`endif

initial	$readmemh (`PAT, pat_mem);


initial begin
   clk         = 1'b0;
   reset       = 1'b0;
   in_en       = 1'b0;
   b_in        = 'hz;
   stop        = 1'b0;
   loop        = 0;
end

always begin #(`CYCLE/2) clk = ~clk; end

initial begin
$dumpfile("GSIM.vcd");
$dumpvars;
//$fsdbDumpfile("GSIM.fsdb");
//$fsdbDumpvars;

for(k = 0; k < 16; k = k + 1)begin
   $dumpvars(0, GSIM.ans[k]);
end

   out_f = $fopen("out.dat");
   if (out_f == 0) begin
        $display("Output file open error !");
        $finish;
   end
end


initial begin
   @(negedge clk)    reset = 1'b1;
   #`CYCLE                reset = 1'b0;
   
   @(negedge clk)  i=0;
    while (i < N_PAT) begin               
         b_in  = pat_mem[i];
         b[i]  = pat_mem[i];
         in_en = 1'b1;
         i=i+1;                  
      @(negedge clk); 
    end     
    in_en = 1'b0;  b_in=16'hz;
end


always @(negedge clk)begin
   if(loop <16)begin
      if(out_valid)begin
         x[loop]=x_out;
         loop=loop+1;
      end
   end
   else begin
         stop=1;
   end
end


initial begin
   @(posedge stop) 
     for (j=0;j<=15;j=j+1)begin
        if(x[j][31]==1) begin   x_f[j]=~x[j] +1'b1;    x_f[j] =-x_f[j]/65536;  end
        else            begin   x_f[j]= x[j];          x_f[j] = x_f[j]/65536;  end
     end
                          
     Mb[0 ]= 20*x_f[0 ]-13*x_f[1 ]+ 6*x_f[2 ]-   x_f[3 ];
     Mb[1 ]=-13*x_f[0 ]+20*x_f[1 ]-13*x_f[2 ]+ 6*x_f[3 ]-   x_f[4 ];
     Mb[2 ]=  6*x_f[0 ]-13*x_f[1 ]+20*x_f[2 ]-13*x_f[3 ]+ 6*x_f[4 ]-  x_f[5 ];      
     Mb[3 ]=   -x_f[0 ]+ 6*x_f[1 ]-13*x_f[2 ]+20*x_f[3 ]-13*x_f[4 ]+6*x_f[5 ]-x_f[6 ];      
     Mb[4 ]=   -x_f[1 ]+ 6*x_f[2 ]-13*x_f[3 ]+20*x_f[4 ]-13*x_f[5 ]+6*x_f[6 ]-x_f[7 ];
     Mb[5 ]=   -x_f[2 ]+ 6*x_f[3 ]-13*x_f[4 ]+20*x_f[5 ]-13*x_f[6 ]+6*x_f[7 ]-x_f[8 ];                    
     Mb[6 ]=   -x_f[3 ]+ 6*x_f[4 ]-13*x_f[5 ]+20*x_f[6 ]-13*x_f[7 ]+6*x_f[8 ]-x_f[9 ];
     Mb[7 ]=   -x_f[4 ]+ 6*x_f[5 ]-13*x_f[6 ]+20*x_f[7 ]-13*x_f[8 ]+6*x_f[9 ]-x_f[10];
     Mb[8 ]=   -x_f[5 ]+ 6*x_f[6 ]-13*x_f[7 ]+20*x_f[8 ]-13*x_f[9 ]+6*x_f[10]-x_f[11];
     Mb[9 ]=   -x_f[6 ]+ 6*x_f[7 ]-13*x_f[8 ]+20*x_f[9 ]-13*x_f[10]+6*x_f[11]-x_f[12];
     Mb[10]=   -x_f[7 ]+ 6*x_f[8 ]-13*x_f[9 ]+20*x_f[10]-13*x_f[11]+6*x_f[12]-x_f[13];
     Mb[11]=   -x_f[8 ]+ 6*x_f[9 ]-13*x_f[10]+20*x_f[11]-13*x_f[12]+6*x_f[13]-x_f[14];
     Mb[12]=   -x_f[9 ]+ 6*x_f[10]-13*x_f[11]+20*x_f[12]-13*x_f[13]+6*x_f[14]-x_f[15];     
     Mb[13]=   -x_f[10]+ 6*x_f[11]-13*x_f[12]+20*x_f[13]-13*x_f[14]+6*x_f[15];
     Mb[14]=   -x_f[11]+ 6*x_f[12]-13*x_f[13]+20*x_f[14]-13*x_f[15];
     Mb[15]=   -x_f[12]+ 6*x_f[13]-13*x_f[14]+20*x_f[15];   
        
     SquareError = 0;        
     
     for(j=0; j<=15; j=j+1)begin     	  
       	if(b[j][15]==1)begin 
       		b_tmp= ~b[j]+1;
       		temp = b_tmp;
       		error= temp + Mb[j];
       	end
       	else begin
       		error = Mb[j] - b[j];
       	end
       	//$display(" Loop=%d    error= %.15f  \n", j, error);
     	  SquareError = SquareError + error*error;
     end
                   
     $display("-----------------------------------------------------\n");
     $display("            Your Output              Golden X\n");
     $display("  X1:     %.10f            402.1120217501   \n", x_f[0 ]);
     $display("  X2:     %.10f           1689.5336804421   \n", x_f[1 ]);
     $display("  X3:     %.10f           2455.4774264763   \n", x_f[2 ]);
     $display("  X4:     %.10f            563.1671481130   \n", x_f[3 ]);
     $display("  X5:     %.10f            703.0136705772   \n", x_f[4 ]);
     $display("  X6:     %.10f           1745.1919122734   \n", x_f[5 ]);
     $display("  X7:     %.10f             33.2002351074   \n", x_f[6 ]);
     $display("  X8:     %.10f            607.1379155812   \n", x_f[7 ]);
     $display("  X9:     %.10f           -477.5895727426   \n", x_f[8 ]);
     $display(" X10:     %.10f            869.0943789319   \n", x_f[9 ]);
     $display(" X11:     %.10f           1907.5237775384   \n", x_f[10]);
     $display(" X12:     %.10f           1524.3408800767   \n", x_f[11]);
     $display(" X13:     %.10f            596.4154551345   \n", x_f[12]);
     $display(" X14:     %.10f           1476.6345624265   \n", x_f[13]);
     $display(" X15:     %.10f           1011.5707976786   \n", x_f[14]);
     $display(" X16:     %.10f          -1330.8985774801   \n", x_f[15]);          
     $display("-----------------------------------------------------\n");
     $display("So Your Error Ratio=  %.15f\n", SquareError);
     $display("-----------------------------------------------------\n");   
     
     error=SquareError;
     if(error<0.000001 && error!='hx && error!='hz)begin                           
         $display("Your Score Level: A \n");  
         $display("Congratulations! GSIM's Function Successfully!\n");
         $display("-------------------------PASS------------------------\n");
     end    
         
     else if(error>=0.000001 && error <0.000005 && error!='hx && error!='hz)begin
        $display("Your Score Level: B \n");
        $display("Congratulations! GSIM's Function Successfully!\n");
        $display("-------------------------PASS------------------------\n");
     end
     else if(error>=0.000005 && error <0.000010 && error!='hx && error!='hz)begin
        $display("Your Score Level: C \n");
        $display("Congratulations! GSIM's Function Successfully!\n");
        $display("-------------------------PASS------------------------\n");
     end 
     else if(error>=0.000010 && error <0.000050 && error!='hx && error!='hz)begin
        $display("Your Score Level: D \n");
        $display("Congratulations! GSIM's Function Successfully!\n");
        $display("-------------------------PASS------------------------\n");
     end 
        
     else if(error>=0.000050 && error <0.000100 && error!='hx && error!='hz)begin
        $display("Your Score Level: E \n");
        $display("Congratulations! GSIM's Function Successfully!\n");
        $display("-------------------------PASS------------------------\n");
     end     
     else if(error>=0.000100 && error <0.001000 && error!='hx && error!='hz)begin
        $display("Your Score Level: F \n");
        $display("Congratulations! GSIM's Function Successfully!\n");
        $display("-------------------------PASS------------------------\n");
     end 
     else if(error>=0.001000 && error <0.005000 && error!='hx && error!='hz)begin
        $display("Your Score Level: G \n");
        $display("Congratulations! GSIM's Function Successfully!\n");
        $display("-------------------------PASS------------------------\n");
     end 
     else if(error>=0.005000 && error <0.010000 && error!='hx && error!='hz)begin
        $display("Your Score Level: H \n");
        $display("Congratulations! GSIM's Function Successfully!\n");
        $display("-------------------------PASS------------------------\n");
     end 
     else if(error>=0.010000 && error <0.100000 && error!='hx && error!='hz)begin
        $display("Your Score Level: I \n");
        $display("Congratulations! GSIM's Function Successfully!\n");
        $display("-------------------------PASS------------------------\n");
     end 
     else if(error>=0.100000 && error <0.300000 && error!='hx && error!='hz)begin
        $display("Your Score Level: J \n");
        $display("Congratulations! GSIM's Function Successfully!\n");
        $display("-------------------------PASS------------------------\n");
     end 
     else begin
        $display("Your Score Level: K \n");                  
        $display("-------------   GSIM's Function Fail   -------------\n");
        $display("-------------------------Fail------------------------\n");
     end
      
      #(`CYCLE/2); $finish;
                       
end
   
endmodule

code/GSIM.vcd
$date
	Wed Apr 30 22:52:17 2025
$end
$version
	Icarus Verilog
$end
$timescale
	10ps
$end
$scope module test $end
$var wire 32 ! x_out [31:0] $end
$var wire 1 " out_valid $end
$var reg 16 # b_in [15:0] $end
$var reg 16 $ b_tmp [15:0] $end
$var reg 1 % clk $end
$var reg 1 & in_en $end
$var reg 1 ' reset $end
$var reg 1 ( stop $end
$var real 1 ) SquareError $end
$var real 1 * error $end
$var integer 32 + i [31:0] $end
$var integer 32 , j [31:0] $end
$var integer 32 - k [31:0] $end
$var integer 32 . loop [31:0] $end
$var integer 32 / out_f [31:0] $end
$var real 1 0 temp $end
$scope module GSIM $end
$var wire 16 1 b_in [15:0] $end
$var wire 1 % clk $end
$var wire 1 & in_en $end
$var wire 1 ' reset $end
$var wire 32 2 x_out [31:0] $end
$var wire 1 " out_valid $end
$var reg 4 3 cnt_r [3:0] $end
$var reg 7 4 cnt_round_r [6:0] $end
$var reg 7 5 cnt_round_w [6:0] $end
$var reg 3 6 cnt_stage_r [2:0] $end
$var reg 3 7 cnt_stage_w [2:0] $end
$var reg 4 8 cnt_w [3:0] $end
$var reg 40 9 r1_r [39:0] $end
$var reg 40 : r1_w [39:0] $end
$var reg 40 ; r2_r [39:0] $end
$var reg 40 < r2_w [39:0] $end
$var reg 40 = r3_r [39:0] $end
$var reg 40 > r3_w [39:0] $end
$var reg 40 ? r4_r [39:0] $end
$var reg 40 @ r4_w [39:0] $end
$var reg 2 A state_r [1:0] $end
$var reg 2 B state_w [1:0] $end
$var reg 40 C w1 [39:0] $end
$var reg 40 D w2 [39:0] $end
$var reg 40 E w3 [39:0] $end
$var reg 40 F w4 [39:0] $end
$var reg 40 G w5 [39:0] $end
$var reg 40 H w6 [39:0] $end
$scope function mul_13 $end
$var reg 40 I a [39:0] $end
$upscope $end
$scope function mul_3 $end
$var reg 40 J a [39:0] $end
$upscope $end
$scope function mul_6 $end
$var reg 40 K a [39:0] $end
$upscope $end
$upscope $end
$upscope $end
$scope module test $end
$scope module GSIM $end
$var reg 40 L \ans[0] [39:0] $end
$upscope $end
$upscope $end
$scope module test $end
$scope module GSIM $end
$var reg 40 M \ans[1] [39:0] $end
$upscope $end
$upscope $end
$scope module test $end
$scope module GSIM $end
$var reg 40 N \ans[2] [39:0] $end
$upscope $end
$upscope $end
$scope module test $end
$scope module GSIM $end
$var reg 40 O \ans[3] [39:0] $end
$upscope $end
$upscope $end
$scope module test $end
$scope module GSIM $end
$var reg 40 P \ans[4] [39:0] $end
$upscope $end
$upscope $end
$scope module test $end
$scope module GSIM $end
$var reg 40 Q \ans[5] [39:0] $end
$upscope $end
$upscope $end
$scope module test $end
$scope module GSIM $end
$var reg 40 R \ans[6] [39:0] $end
$upscope $end
$upscope $end
$scope module test $end
$scope module GSIM $end
$var reg 40 S \ans[7] [39:0] $end
$upscope $end
$upscope $end
$scope module test $end
$scope module GSIM $end
$var reg 40 T \ans[8] [39:0] $end
$upscope $end
$upscope $end
$scope module test $end
$scope module GSIM $end
$var reg 40 U \ans[9] [39:0] $end
$upscope $end
$upscope $end
$scope module test $end
$scope module GSIM $end
$var reg 40 V \ans[10] [39:0] $end
$upscope $end
$upscope $end
$scope module test $end
$scope module GSIM $end
$var reg 40 W \ans[11] [39:0] $end
$upscope $end
$upscope $end
$scope module test $end
$scope module GSIM $end
$var reg 40 X \ans[12] [39:0] $end
$upscope $end
$upscope $end
$scope module test $end
$scope module GSIM $end
$var reg 40 Y \ans[13] [39:0] $end
$upscope $end
$upscope $end
$scope module test $end
$scope module GSIM $end
$var reg 40 Z \ans[14] [39:0] $end
$upscope $end
$upscope $end
$scope module test $end
$scope module GSIM $end
$var reg 40 [ \ans[15] [39:0] $end
$upscope $end
$upscope $end
$enddefinitions $end
#0
$dumpvars
bx [
bx Z
bx Y
bx X
bx W
bx V
bx U
bx T
bx S
bx R
bx Q
bx P
bx O
bx N
bx M
bx L
bx K
bx J
bx I
bx H
bx G
bx F
bx E
bx D
bx C
bx B
bx A
bx @
bx ?
bx >
bx =
bx <
bx ;
bx :
bx 9
bx 8
bx 7
bx 6
bx 5
bx 4
bx 3
bx 2
bz 1
r0 0
b10 /
b0 .
b10000 -
bx ,
bx +
r0 *
r0 )
0(
0'
0&
0%
bx $
bz #
x"
bx !
$end
#500
1%
#1000
b0 E
b0 D
b0 C
b0 5
b0 7
b0 8
b0 B
b0 @
b0 >
b0 <
b0 :
b0 ?
b0 =
b0 ;
b0 9
b0 3
b0 4
b0 6
0"
b0 A
1'
0%
#1500
1%
#2000
b1 8
1&
b11111000 #
b11111000 1
b1 +
0%
0'
#2500
b10 8
b1 3
b0 L
1%
#3000
b10 +
b1111110101010110 #
b1111110101010110 1
0%
#3500
b11 8
b10 3
b0 M
1%
#4000
b11 +
b110000010000110 #
b110000010000110 1
0%
#4500
b100 8
b11 3
b0 N
1%
#5000
b100 +
b1101101001101000 #
b1101101001101000 1
0%
#5500
b101 8
b100 3
b0 O
1%
#6000
b101 +
b1111001100001111 #
b1111001100001111 1
0%
#6500
b110 8
b101 3
b0 P
1%
#7000
b110 +
b111011010101001 #
b111011010101001 1
0%
#7500
b111 8
b110 3
b0 Q
1%
#8000
b111 +
b1000101011010100 #
b1000101011010100 1
0%
#8500
b1000 8
b111 3
b0 R
1%
#9000
b1000 +
b111100100010011 #
b111100100010011 1
0%
#9500
b1001 8
b1000 3
b0 S
1%
#10000
b1001 +
b1011000001110000 #
b1011000001110000 1
0%
#10500
b1010 8
b1001 3
b0 T
1%
#11000
b1010 +
b10101011001000 #
b10101011001000 1
0%
#11500
b1011 8
b1010 3
b0 U
1%
#12000
b1011 +
b1011000100001 #
b1011000100001 1
0%
#12500
b1100 8
b1011 3
b0 V
1%
#13000
b1100 +
b10110011010100 #
b10110011010100 1
0%
#13500
b1101 8
b1100 3
b0 W
1%
#14000
b1101 +
b1101110001101100 #
b1101110001101100 1
0%
#14500
b1110 8
b0 H
b1101 3
b0 X
1%
#15000
b1110 +
b1111011001010 #
b1111011001010 1
0%
#15500
b1111 8
b0 G
b1110 3
b0 Y
1%
#16000
b1111 +
b100111110100111 #
b100111110100111 1
0%
#16500
b0 8
b1 B
b0 F
b1111 3
b0 Z
1%
#17000
b10000 +
b1000010011101111 #
b1000010011101111 1
0%
#17500
b1 7
b0 !
b0 2
b0 I
b0 J
b0 K
b111110000000000000000000 :
b0 3
b1 A
b0 [
1%
#18000
b1 7
bz #
bz 1
0&
0%
#18500
b10 7
b111110000000000000000000 @
b1 6
b111110000000000000000000 9
1%
#19000
0%
#19500
b11 7
b1000001111000000000000000 @
b10 6
b111110000000000000000000 ?
1%
#20000
0%
#20500
b100 7
b1000010001000011110000000 @
b11 6
b1000001111000000000000000 ?
1%
#21000
0%
#21500
b1 8
b0 7
b11000110011001100110 @
b100 6
b1000010001000011110000000 ?
1%
#22000
0%
#22500
b101000010011001100101110 >
b11000110011001100110 I
b1 7
b11000110011001100110 C
b1111111111111101010101100000000000000000 :
b1 3
b0 6
b11000110011001100110 L
b11000110011001100110 ?
1%
#23000
0%
#23500
b10 7
b1111111111111101111101110011001100101110 @
b1 6
b101000010011001100101110 =
b1111111111111101010101100000000000000000 9
1%
#24000
0%
#24500
b11 7
b1111111111111101110101101010011001100000 @
b10 6
b1111111111111101111101110011001100101110 ?
1%
#25000
0%
#25500
b100 7
b1111111111111101110101000111110100000110 @
b11 6
b1111111111111101110101101010011001100000 ?
1%
#26000
0%
#26500
b10 8
b0 7
b1111111111111111111001011111010111000001 @
b100 6
b1111111111111101110101000111110100000110 ?
1%
#27000
0%
#27500
b1111111111111110101011010111101011001101 >
b1111111111111111111001011111010111000001 I
b10010100110011001100100 <
b11000110011001100110 J
b11000110011001100110 K
b1 7
b11000110011001100110 D
b1111111111111111111001011111010111000001 C
b1100000100001100000000000000000 :
b10 3
b0 6
b1111111111111111111001011111010111000001 M
b1111111111111111111001011111010111000001 ?
1%
#28000
0%
#28500
b10 7
b1011110111010010001010001101001 @
b1 6
b1111111111111110101011010111101011001101 =
b10010100110011001100100 ;
b1100000100001100000000000000000 9
1%
#29000
0%
#29500
b11 7
b1100100110101111010010110101111 @
b10 6
b1011110111010010001010001101001 ?
1%
#30000
0%
#30500
b100 7
b1100101001111000111110101010100 @
b11 6
b1100100110101111010010110101111 ?
1%
#31000
0%
#31500
b11 8
b0 7
b100101111101101101010011100 @
b100 6
b1100101001111000111110101010100 ?
1%
#32000
0%
#32500
b111101101100010001100111101100 >
b100101111101101101010011100 I
b1111111111111111011000111100001010000110 <
b1111111111111111111001011111010111000001 J
b1111111111111111111001011111010111000001 K
b1 7
b11000110011001100110 E
b1111111111111111111001011111010111000001 D
b100101111101101101010011100 C
b1111111111011010011101000110011001100110 :
b11 3
b0 6
b100101111101101101010011100 N
b100101111101101101010011100 ?
1%
#33000
0%
#33500
b10 7
b11000110000011011110111001100 @
b1 6
b111101101100010001100111101100 =
b1111111111111111011000111100001010000110 ;
b1111111111011010011101000110011001100110 9
1%
#34000
0%
#34500
b11 7
b11010010011011101100110101000 @
b10 6
b11000110000011011110111001100 ?
1%
#35000
0%
#35500
b100 7
b11010011010000010011110000001 @
b11 6
b11010010011011101100110101000 ?
1%
#36000
0%
#36500
b100 8
b0 7
b1001111001110001100010110 @
b100 6
b11010011010000010011110000001 ?
1%
#37000
0%
#37500
b10000000101111000100000011110 >
b1001111001110001100010110 I
b11100011110010001111110101000 <
b100101111101101101010011100 J
b100101111101101101010011100 K
b1 7
b1111111111111111111001011111010111000001 E
b100101111101101101010011100 D
b1001111001110001100010110 C
b1111111111110010111101001111010111000001 :
b100 3
b0 6
b1001111001110001100010110 O
b1001111001110001100010110 ?
1%
#38000
0%
#38500
b10 7
b1111111111100110100100110101111000110111 @
b1 6
b10000000101111000100000011110 =
b11100011110010001111110101000 ;
b1111111111110010111101001111010111000001 9
1%
#39000
0%
#39500
b11 7
b1111111111100100111111001001010000011010 @
b10 6
b1111111111100110100100110101111000110111 ?
1%
#40000
0%
#40500
b100 7
b1111111111100100111000011001000010101110 @
b11 6
b1111111111100100111111001001010000011010 ?
1%
#41000
0%
#41500
b101 8
b0 7
b1111111111111110101110101001000110000001 @
b100 6
b1111111111100100111000011001000010101110 ?
1%
#42000
0%
#42500
b1111111111101111011110010110001110001101 >
b1111111111111110101110101001000110000001 I
b111011011010101001010000100 <
b1001111001110001100010110 J
b1001111001110001100010110 K
b1 7
b100101111101101101010011100 E
b1001111001110001100010110 D
b1111111111111110101110101001000110000001 C
b1111011011001111101101010011100 :
b101 3
b0 6
b1111111111111110101110101001000110000001 P
b1111111111111110101110101001000110000001 ?
1%
#43000
0%
#43500
b10 7
b1100011011100111110101110100101 @
b1 6
b1111111111101111011110010110001110001101 =
b111011011010101001010000100 ;
b1111011011001111101101010011100 9
1%
#44000
0%
#44500
b11 7
b1101001101010110010101001011111 @
b10 6
b1100011011100111110101110100101 ?
1%
#45000
0%
#45500
b100 7
b1101010000101001101010110001001 @
b11 6
b1101001101010110010101001011111 ?
1%
#46000
0%
#46500
b110 8
b0 7
b100111110001111111011111010 @
b100 6
b1101010000101001101010110001001 ?
1%
#47000
0%
#47500
b1000000101001001111001010110010 >
b100111110001111111011111010 I
b1111111111111000010111110110100100000110 <
b1111111111111110101110101001000110000001 J
b1111111111111110101110101001000110000001 K
b1 7
b1001111001110001100010110 E
b1111111111111110101110101001000110000001 D
b100111110001111111011111010 C
b1111111110001100000100001110001100010110 :
b110 3
b0 6
b100111110001111111011111010 Q
b100111110001111111011111010 ?
1%
#48000
0%
#48500
b10 7
b1111111111010100010101100110110011000010 @
b1 6
b1000000101001001111001010110010 =
b1111111111111000010111110110100100000110 ;
b1111111110001100000100001110001100010110 9
1%
#49000
0%
#49500
b11 7
b1111111111010001100110111101001110001110 @
b10 6
b1111111111010100010101100110110011000010 ?
1%
#50000
0%
#50500
b100 7
b1111111111010001011011010110111101100001 @
b11 6
b1111111111010001100110111101001110001110 ?
1%
#51000
0%
#51500
b111 8
b0 7
b1111111111111101110100010001111100001000 @
b100 6
b1111111111010001011011010110111101100001 ?
1%
#52000
0%
#52500
b1111111111100011100111101001001101101000 >
b1111111111111101110100010001111100001000 I
b11101110101011111100111011100 <
b100111110001111111011111010 J
b100111110001111111011111010 K
b1 7
b1111111111111110101110101001000110000001 E
b100111110001111111011111010 D
b1111111111111101110100010001111100001000 C
b1110111110011011001000110000001 :
b111 3
b0 6
b1111111111111101110100010001111100001000 R
b1111111111111101110100010001111100001000 ?
1%
#53000
0%
#53500
b10 7
b111101100101100010101100001101 @
b1 6
b1111111111100011100111101001001101101000 =
b11101110101011111100111011100 ;
b1110111110011011001000110000001 9
1%
#54000
0%
#54500
b11 7
b1000001011011111000110110111101 @
b10 6
b111101100101100010101100001101 ?
1%
#55000
0%
#55500
b100 7
b1000001101100001111110101001010 @
b11 6
b1000001011011111000110110111101 ?
1%
#56000
0%
#56500
b1000 8
b0 7
b11000101000100111011110010 @
b100 6
b1000001101100001111110101001010 ?
1%
#57000
0%
#57500
b101000000010000000001001001010 >
b11000101000100111011110010 I
b1111111111110010111001101011101000110000 <
b1111111111111101110100010001111100001000 J
b1111111111111101110100010001111100001000 K
b1 7
b100111110001111111011111010 E
b1111111111111101110100010001111100001000 D
b11000101000100111011110010 C
b1111111110110101011010001111111011111010 :
b1000 3
b0 6
b11000101000100111011110010 S
b11000101000100111011110010 ?
1%
#58000
0%
#58500
b10 7
b1111111111101010100010100100011100010100 @
b1 6
b101000000010000000001001001010 =
b1111111111110010111001101011101000110000 ;
b1111111110110101011010001111111011111010 9
1%
#59000
0%
#59500
b11 7
b1111111111101001001100101110101110000101 @
b10 6
b1111111111101010100010100100011100010100 ?
1%
#60000
0%
#60500
b100 7
b1111111111101001000111000001111001110000 @
b11 6
b1111111111101001001100101110101110000101 ?
1%
#61000
0%
#61500
b1001 8
b0 7
b1111111111111110111011010101000001011000 @
b100 6
b1111111111101001000111000001111001110000 ?
1%
#62000
0%
#62500
b1111111111110010000011010001010001111000 >
b1111111111111110111011010101000001011000 I
b10010011110011101100110101100 <
b11000101000100111011110010 J
b11000101000100111011110010 K
b1 7
b1111111111111101110100010001111100001000 E
b11000101000100111011110010 D
b1111111111111110111011010101000001011000 C
b101000100110010001111100001000 :
b1001 3
b0 6
b1111111111111110111011010101000001011000 T
b1111111111111110111011010101000001011000 ?
1%
#63000
0%
#63500
b10 7
b1000001011000101100111010100 @
b1 6
b1111111111110010000011010001010001111000 =
b10010011110011101100110101100 ;
b101000100110010001111100001000 9
1%
#64000
0%
#64500
b11 7
b1000101011110001111101110001 @
b10 6
b1000001011000101100111010100 ?
1%
#65000
0%
#65500
b100 7
b1000101101111100111010010000 @
b11 6
b1000101011110001111101110001 ?
1%
#66000
0%
#66500
b1010 8
b0 7
b11010001001111000010101 @
b100 6
b1000101101111100111010010000 ?
1%
#67000
0%
#67500
b101010100000000011100010001 >
b11010001001111000010101 I
b1111111111111001100011111110001000010000 <
b1111111111111110111011010101000001011000 J
b1111111111111110111011010101000001011000 K
b1 7
b11000101000100111011110010 E
b1111111111111110111011010101000001011000 D
b11010001001111000010101 C
b11001001101010100111011110010 :
b1010 3
b0 6
b11010001001111000010101 U
b11010001001111000010101 ?
1%
#68000
0%
#68500
b10 7
b100100111101010111001111110011 @
b1 6
b101010100000000011100010001 =
b1111111111111001100011111110001000010000 ;
b11001001101010100111011110010 9
1%
#69000
0%
#69500
b11 7
b100111010001001100101100110010 @
b10 6
b100100111101010111001111110011 ?
1%
#70000
0%
#70500
b100 7
b100111011011000000111111111101 @
b11 6
b100111010001001100101100110010 ?
1%
#71000
0%
#71500
b1011 8
b0 7
b1110110010001001010010110 @
b100 6
b100111011011000000111111111101 ?
1%
#72000
0%
#72500
b11000000001011111000110011110 >
b1110110010001001010010110 I
b10011100111011010001111110 <
b11010001001111000010101 J
b11010001001111000010101 K
b1 7
b1111111111111110111011010101000001011000 E
b11010001001111000010101 D
b1110110010001001010010110 C
b101011110000010101000001011000 :
b1011 3
b0 6
b1110110010001001010010110 V
b1110110010001001010010110 ?
1%
#73000
0%
