code/GSIM_pipeline.v
module GSIM(clk, reset, in_en, b_in, out_valid, x_out);
    input               clk;
    input               reset;
    input               in_en;
    input signed [15:0] b_in;
    output              out_valid;
    output       [31:0] x_out;

    reg [1:0] state_r, state_w;

    localparam RECEIVE = 0;
    localparam CALC    = 1; //Do Gauss Seidel approximtiatin
    localparam SEND    = 2;

    reg signed [15:0] b            [0:15];   //store offsets b1 b2... b16 16bits each
    reg signed [31:0] ans          [0:15];   //store answers x1 x2... x16 32bits each

    reg signed [35:0] pipeline_r   [0:5 ];
    reg signed [35:0] pipeline_w   [0:5 ];
    reg signed [35:0] pipeline_src [0:5 ];

    reg signed [35:0] pipeline_support_1;
    reg signed [35:0] pipeline_support_2;
    reg signed [35:0] pipeline_support_3;
    reg        [11:0] cnt_r, cnt_w;
    reg        [ 3:0] mapping;

    wire [3:0] idx0 = (cnt_r[3] | cnt_r[2]) ? 4'd13 : 4'd12;
    wire [3:0] idx1 = (cnt_r[3] & cnt_r[2]) ? 4'd4 : 4'd3;
    wire [3:0] idx2 = (cnt_r[3])? 4'd9 : 4'd8 ;
    wire [3:0] idx3 = (cnt_r[3])? 4'd8 : 4'd7 ;
    wire [3:0] idx4 = (cnt_r[3] & cnt_r[2]) ? 4'd5 : 4'd4;
    wire [3:0] idx5 = (cnt_r[3] | cnt_r[2]) ? 4'd12 : 4'd11;

    localparam MAX_ITER     = 77; //maximum number of iterations
    localparam PIPELINE_MAX = (16 * MAX_ITER) - 1;

    assign out_valid = (state_r == SEND) ? 1 : 0; //output valid when in SEND state
    assign x_out = ans[mapping];

    function signed [35:0] mul_3_2;
        input signed [35:0] a;
        begin
            mul_3_2 = (a>>>2) + (a>>>1);
        end
    endfunction

    function signed [35:0] mul_18_2;
        input signed [35:0] a;
        begin
            mul_18_2 = (a<<<2) + (a>>>1);
        end
    endfunction

    function signed [35:0] mul_39_2;
        input signed [35:0] a;
        begin
            mul_39_2 = (a<<<3)  + a  + (a>>>1)  + (a>>>2);
        end
    endfunction

    //pipeline choose
    always @(*) begin
        pipeline_src[0] = {{2{ans[idx0][31]}},ans[idx0],2'sd0};  // future 3
        pipeline_src[1] = {{2{ans[idx1][31]}},ans[idx1],2'sd0};  // past 3
        pipeline_src[2] = {{2{ans[idx2][31]}},ans[idx2],2'sd0};  // future 2
        pipeline_src[3] = {{2{ans[idx3][31]}},ans[idx3],2'sd0};  // past 2
        pipeline_src[4] = {{2{ans[idx4][31]}},ans[idx4],2'sd0};  // future 1
        pipeline_src[5] = {{2{ans[idx5][31]}},ans[idx5],2'sd0};  // past 1

        case (cnt_r[3:0])  
            0: begin
                pipeline_src[1] = 0;
                pipeline_src[3] = 0;
                pipeline_src[5] = 0;
            end
            4: begin
                pipeline_src[1] = 0;
                pipeline_src[3] = 0;
            end
            7: begin
                pipeline_src[0] = 0;
            end
            8: begin
                pipeline_src[1] = 0;
            end
            11: begin
                pipeline_src[0] = 0;
                pipeline_src[2] = 0;
            end
            15: begin
                pipeline_src[0] = 0;
                pipeline_src[2] = 0;
                pipeline_src[4] = 0;
            end
        endcase
    end

    //pipeline count
    always @(*) begin

        pipeline_w[0] = mul_3_2({{2{b[mapping][15]}},b[mapping],18'sd0});
        pipeline_w[1] = mul_3_2(pipeline_src[0] + pipeline_src[1]);
        pipeline_w[2] = mul_18_2(pipeline_src[2] + pipeline_src[3]);
        pipeline_w[3] = mul_39_2(pipeline_src[4] + pipeline_src[5]);

        pipeline_support_1 = ((pipeline_r[0] - pipeline_r[2]) >>>2) + ((pipeline_r[1] + pipeline_r[3]) >>>2);
        pipeline_w[4] = pipeline_support_1 + (pipeline_support_1 >>> 4);

        pipeline_w[5] = pipeline_r[4] + (pipeline_r[4] >>> 8);

        pipeline_support_2 = pipeline_r[5] + (pipeline_r[5] >>> 16);
        pipeline_support_3 = pipeline_support_2 >>> 2;

    end

    //FSM
    always @(*) begin
        state_w = state_r;
        cnt_w   = cnt_r;

        case (state_r)
            RECEIVE: begin
                if (in_en) begin
                    if (cnt_r == 15) begin
                        state_w = CALC;
                        cnt_w   = 0;
                    end
                    else begin
                        cnt_w = cnt_r + 1;
                    end
                end
            end

            CALC: begin
                if (cnt_r == PIPELINE_MAX) begin
                    state_w = SEND;
                    cnt_w   = 0;
                end
                else begin
                    cnt_w = cnt_r + 1;
                end
            end

            SEND: begin
                if (cnt_r == 15) begin
                    state_w = RECEIVE;
                    cnt_w   = 0;
                end
                else begin
                    cnt_w = cnt_r + 1;
                end
            end
        endcase
    end

    always @(*) begin
        case (cnt_r[3:0])
            4'd0:  mapping = 4'd0;
            4'd1:  mapping = 4'd4;
            4'd2:  mapping = 4'd8;
            4'd3:  mapping = 4'd12;
            4'd4:  mapping = 4'd1;
            4'd5:  mapping = 4'd5;
            4'd6:  mapping = 4'd9;
            4'd7:  mapping = 4'd13;
            4'd8:  mapping = 4'd2;
            4'd9:  mapping = 4'd6;
            4'd10: mapping = 4'd10;
            4'd11: mapping = 4'd14;
            4'd12: mapping = 4'd3;
            4'd13: mapping = 4'd7;
            4'd14: mapping = 4'd11;
            4'd15: mapping = 4'd15;
        endcase
    end

    //b_in
    always @(posedge clk or posedge reset) begin
        if (reset) begin
            b[0]  <= 0;
            b[1]  <= 0;
            b[2]  <= 0;
            b[3]  <= 0;
            b[4]  <= 0;
            b[5]  <= 0;
            b[6]  <= 0;
            b[7]  <= 0;
            b[8]  <= 0;
            b[9]  <= 0;
            b[10] <= 0;
            b[11] <= 0;
            b[12] <= 0;
            b[13] <= 0;
            b[14] <= 0;
            b[15] <= 0;
        end
        else begin
            if (state_r == RECEIVE && in_en) begin
                b[cnt_r] <= b_in;
            end
        end
    end

    always @(posedge clk or posedge reset) begin
        if (reset) begin
            state_r       <= RECEIVE;
            cnt_r         <= 0;
            pipeline_r[0] <= 0;
            pipeline_r[1] <= 0;
            pipeline_r[2] <= 0;
            pipeline_r[3] <= 0;
            pipeline_r[4] <= 0;
            pipeline_r[5] <= 0;
        end
        else begin
            state_r       <= state_w;
            cnt_r         <= cnt_w;
            pipeline_r[0] <= pipeline_w[0];
            pipeline_r[1] <= pipeline_w[1];
            pipeline_r[2] <= pipeline_w[2];
            pipeline_r[3] <= pipeline_w[3];
            pipeline_r[4] <= pipeline_w[4];
            pipeline_r[5] <= pipeline_w[5];
        end
    end

    always @(posedge clk or posedge reset) begin
        if (reset) begin
            ans[0]  <= 0;
            ans[1]  <= 0;
            ans[2]  <= 0;
            ans[3]  <= 0;
            ans[4]  <= 0;
            ans[5]  <= 0;
            ans[6]  <= 0;
            ans[7]  <= 0;
            ans[8]  <= 0;
            ans[9]  <= 0;
            ans[10] <= 0;
            ans[11] <= 0;
            ans[12] <= 0;
            ans[13] <= 0;
            ans[14] <= 0;
            ans[15] <= 0;
        end
        else begin
            if (state_r == CALC) begin
                ans[0]  <= ans[1];
                ans[1]  <= ans[2];
                ans[2]  <= ans[3];
                ans[3]  <= ans[4];
                ans[4]  <= ans[5];
                ans[5]  <= ans[6];
                ans[6]  <= ans[7];
                ans[7]  <= ans[8];
                ans[8]  <= ans[9];
                ans[9]  <= ans[10];
                ans[10] <= ans[11];
                ans[11] <= ans[12];
                ans[12] <= pipeline_support_3[33:2];
                ans[13] <= ans[14];
                ans[14] <= ans[15];
                ans[15] <= ans[0];
            end
        end
    end
endmodule

code/testfixture2.v
`timescale 1ns/10ps
`define CYCLE    0.7           	         // Modify your clock period here
`define SDFFILE  "./Netlist/GSIM_syn.sdf"	      // Modify your sdf file name
`define PAT      "./pattern2.dat"    
module test;
parameter N_PAT   = 16;

reg   clk ;
reg   reset ;
reg   in_en;
reg   [15:0]  b_in;
wire  out_valid;
wire  [31:0]  x_out;

reg   [15:0]  pat_mem   [0:N_PAT-1];
reg   [31:0]  x         [0:N_PAT-1];
reg   [15:0]  b         [0:N_PAT-1];
reg   [15:0]  b_tmp;
integer       loop, i, j, out_f;
reg           stop;
real  Mb [0:15];
real  x_f[0:15];
real  SquareError, error, temp;


   GSIM GSIM( .clk(clk), .reset(reset), .in_en(in_en), .b_in(b_in),
              .out_valid(out_valid), .x_out(x_out));
   

`ifdef SDF
   initial $sdf_annotate(`SDFFILE, GSIM);
`endif

initial	$readmemh (`PAT, pat_mem);


initial begin
   clk         = 1'b0;
   reset       = 1'b0;
   in_en       = 1'b0;   
   b_in        = 'hz;
   stop        = 1'b0;   
   loop        = 0;
end

always begin #(`CYCLE/2.0) clk = ~clk; end

initial begin
$dumpfile("GSIM.vcd");
$dumpvars;
//$fsdbDumpfile("GSIM.fsdb");
//$fsdbDumpvars;

   out_f = $fopen("out.dat");
   if (out_f == 0) begin
        $display("Output file open error !");
        $finish;
   end
end


initial begin
   @(negedge clk)   reset = 1'b1;
   #`CYCLE                reset = 1'b0;
   
   @(negedge clk)   i=0;
    while (i < N_PAT) begin               
         b_in  = pat_mem[i];
         b[i]  = pat_mem[i];
         in_en = 1'b1;
         i=i+1;                  
      @(negedge clk);
    end     
    in_en = 1'b0;  b_in=16'hz;
end


always @(negedge clk)begin
   if(loop <16)begin
      if(out_valid)begin
         x[loop]=x_out;
         loop=loop+1;
      end
   end
   else begin
         stop=1;
   end
end


initial begin
   @(posedge stop) 
     for (j=0;j<=15;j=j+1)begin
        if(x[j][31]==1) begin   x_f[j]=~x[j] +1'b1;    x_f[j] =-x_f[j]/65536;  end
        else            begin   x_f[j]= x[j];          x_f[j] = x_f[j]/65536;  end
     end
                          
     Mb[0 ]= 20*x_f[0 ]-13*x_f[1 ]+ 6*x_f[2 ]-   x_f[3 ];
     Mb[1 ]=-13*x_f[0 ]+20*x_f[1 ]-13*x_f[2 ]+ 6*x_f[3 ]-   x_f[4 ];
     Mb[2 ]=  6*x_f[0 ]-13*x_f[1 ]+20*x_f[2 ]-13*x_f[3 ]+ 6*x_f[4 ]-  x_f[5 ];      
     Mb[3 ]=   -x_f[0 ]+ 6*x_f[1 ]-13*x_f[2 ]+20*x_f[3 ]-13*x_f[4 ]+6*x_f[5 ]-x_f[6 ];      
     Mb[4 ]=   -x_f[1 ]+ 6*x_f[2 ]-13*x_f[3 ]+20*x_f[4 ]-13*x_f[5 ]+6*x_f[6 ]-x_f[7 ];
     Mb[5 ]=   -x_f[2 ]+ 6*x_f[3 ]-13*x_f[4 ]+20*x_f[5 ]-13*x_f[6 ]+6*x_f[7 ]-x_f[8 ];                    
     Mb[6 ]=   -x_f[3 ]+ 6*x_f[4 ]-13*x_f[5 ]+20*x_f[6 ]-13*x_f[7 ]+6*x_f[8 ]-x_f[9 ];
     Mb[7 ]=   -x_f[4 ]+ 6*x_f[5 ]-13*x_f[6 ]+20*x_f[7 ]-13*x_f[8 ]+6*x_f[9 ]-x_f[10];
     Mb[8 ]=   -x_f[5 ]+ 6*x_f[6 ]-13*x_f[7 ]+20*x_f[8 ]-13*x_f[9 ]+6*x_f[10]-x_f[11];
     Mb[9 ]=   -x_f[6 ]+ 6*x_f[7 ]-13*x_f[8 ]+20*x_f[9 ]-13*x_f[10]+6*x_f[11]-x_f[12];
     Mb[10]=   -x_f[7 ]+ 6*x_f[8 ]-13*x_f[9 ]+20*x_f[10]-13*x_f[11]+6*x_f[12]-x_f[13];
     Mb[11]=   -x_f[8 ]+ 6*x_f[9 ]-13*x_f[10]+20*x_f[11]-13*x_f[12]+6*x_f[13]-x_f[14];
     Mb[12]=   -x_f[9 ]+ 6*x_f[10]-13*x_f[11]+20*x_f[12]-13*x_f[13]+6*x_f[14]-x_f[15];     
     Mb[13]=   -x_f[10]+ 6*x_f[11]-13*x_f[12]+20*x_f[13]-13*x_f[14]+6*x_f[15];
     Mb[14]=   -x_f[11]+ 6*x_f[12]-13*x_f[13]+20*x_f[14]-13*x_f[15];
     Mb[15]=   -x_f[12]+ 6*x_f[13]-13*x_f[14]+20*x_f[15];   
        
     SquareError = 0;        
     
     for(j=0; j<=15; j=j+1)begin     	  
       	if(b[j][15]==1)begin 
       		b_tmp= ~b[j]+1;
       		temp = b_tmp;
       		error= temp + Mb[j];
       	end
       	else begin
       		error = Mb[j] - b[j];
       	end
       	//$display(" Loop=%d    error= %.15f  \n", j, error);
     	  SquareError = SquareError + error*error;
     end
                   
     $display("-----------------------------------------------------\n");
     $display("        Your Output           Golden X\n");
     $display("  X1:     %.10f           2912.9564416992 \n", x_f[0 ]);
     $display("  X2:     %.10f           3563.4672138156 \n", x_f[1 ]);
     $display("  X3:     %.10f           1975.2084612612 \n", x_f[2 ]);
     $display("  X4:     %.10f           3160.3058219490 \n", x_f[3 ]);
     $display("  X5:     %.10f             91.0354695204 \n", x_f[4 ]);
     $display("  X6:     %.10f          -5435.9287723975 \n", x_f[5 ]);
     $display("  X7:     %.10f          -4893.7804543717 \n", x_f[6 ]);
     $display("  X8:     %.10f           1654.9085737604 \n", x_f[7 ]);
     $display("  X9:     %.10f           7008.1872681125 \n", x_f[8 ]);
     $display(" X10:     %.10f           5228.6840986953 \n", x_f[9 ]);
     $display(" X11:     %.10f           1204.3793848452 \n", x_f[10]);
     $display(" X12:     %.10f           3993.5629755645 \n", x_f[11]);
     $display(" X13:     %.10f           6128.9252357761 \n", x_f[12]);
     $display(" X14:     %.10f           3804.1421810991 \n", x_f[13]);
     $display(" X15:     %.10f            887.0698538670 \n", x_f[14]);
     $display(" X16:     %.10f          -1431.6509875273 \n", x_f[15]);          
     $display("-----------------------------------------------------\n");
     $display("So Your Error Ratio=  %.15f\n", SquareError);
     $display("-----------------------------------------------------\n");   
     
     error=SquareError;
     if(error<0.000001 && error!='hx && error!='hz)begin                           
         $display("Your Score Level: A \n");  
         $display("Congratulations! GSIM's Function Successfully!\n");
         $display("-------------------------PASS------------------------\n");
     end    
         
     else if(error>=0.000001 && error <0.000005 && error!='hx && error!='hz)begin
        $display("Your Score Level: B \n");
        $display("Congratulations! GSIM's Function Successfully!\n");
        $display("-------------------------PASS------------------------\n");
     end
     else if(error>=0.000005 && error <0.000010 && error!='hx && error!='hz)begin
        $display("Your Score Level: C \n");
        $display("Congratulations! GSIM's Function Successfully!\n");
        $display("-------------------------PASS------------------------\n");
     end 
     else if(error>=0.000010 && error <0.000050 && error!='hx && error!='hz)begin
        $display("Your Score Level: D \n");
        $display("Congratulations! GSIM's Function Successfully!\n");
        $display("-------------------------PASS------------------------\n");
     end 
        
     else if(error>=0.000050 && error <0.000100 && error!='hx && error!='hz)begin
        $display("Your Score Level: E \n");
        $display("Congratulations! GSIM's Function Successfully!\n");
        $display("-------------------------PASS------------------------\n");
     end     
     else if(error>=0.000100 && error <0.001000 && error!='hx && error!='hz)begin
        $display("Your Score Level: F \n");
        $display("Congratulations! GSIM's Function Successfully!\n");
        $display("-------------------------PASS------------------------\n");
     end 
     else if(error>=0.001000 && error <0.005000 && error!='hx && error!='hz)begin
        $display("Your Score Level: G \n");
        $display("Congratulations! GSIM's Function Successfully!\n");
        $display("-------------------------PASS------------------------\n");
     end 
     else if(error>=0.005000 && error <0.010000 && error!='hx && error!='hz)begin
        $display("Your Score Level: H \n");
        $display("Congratulations! GSIM's Function Successfully!\n");
        $display("-------------------------PASS------------------------\n");
     end 
     else if(error>=0.010000 && error <0.100000 && error!='hx && error!='hz)begin
        $display("Your Score Level: I \n");
        $display("Congratulations! GSIM's Function Successfully!\n");
        $display("-------------------------PASS------------------------\n");
     end 
     else if(error>=0.100000 && error <0.300000 && error!='hx && error!='hz)begin
        $display("Your Score Level: J \n");
        $display("Congratulations! GSIM's Function Successfully!\n");
        $display("-------------------------PASS------------------------\n");
     end 
     else begin
        $display("Your Score Level: K \n");                  
        $display("-------------   GSIM's Function Fail   -------------\n");
        $display("-------------------------Fail------------------------\n");
     end
      
      #(`CYCLE/2); $finish;
                       
end
   
endmodule

code/GSIM.vcd
$date
	Thu May  1 15:04:16 2025
$end
$version
	Icarus Verilog
$end
$timescale
	10ps
$end
$scope module test $end
$var wire 32 ! x_out [31:0] $end
$var wire 1 " out_valid $end
$var reg 16 # b_in [15:0] $end
$var reg 16 $ b_tmp [15:0] $end
$var reg 1 % clk $end
$var reg 1 & in_en $end
$var reg 1 ' reset $end
$var reg 1 ( stop $end
$var real 1 ) SquareError $end
$var real 1 * error $end
$var integer 32 + i [31:0] $end
$var integer 32 , j [31:0] $end
$var integer 32 - loop [31:0] $end
$var integer 32 . out_f [31:0] $end
$var real 1 / temp $end
$scope module GSIM $end
$var wire 16 0 b_in [15:0] $end
$var wire 1 % clk $end
$var wire 1 & in_en $end
$var wire 1 ' reset $end
$var wire 32 1 x_out [31:0] $end
$var wire 1 " out_valid $end
$var wire 4 2 idx5 [3:0] $end
$var wire 4 3 idx4 [3:0] $end
$var wire 4 4 idx3 [3:0] $end
$var wire 4 5 idx2 [3:0] $end
$var wire 4 6 idx1 [3:0] $end
$var wire 4 7 idx0 [3:0] $end
$var reg 12 8 cnt_r [11:0] $end
$var reg 12 9 cnt_w [11:0] $end
$var reg 4 : mapping [3:0] $end
$var reg 36 ; pipeline_support_1 [35:0] $end
$var reg 36 < pipeline_support_2 [35:0] $end
$var reg 36 = pipeline_support_3 [35:0] $end
$var reg 2 > state_r [1:0] $end
$var reg 2 ? state_w [1:0] $end
$scope function mul_18_2 $end
$var reg 36 @ a [35:0] $end
$upscope $end
$scope function mul_39_2 $end
$var reg 36 A a [35:0] $end
$upscope $end
$scope function mul_3_2 $end
$var reg 36 B a [35:0] $end
$upscope $end
$upscope $end
$upscope $end
$enddefinitions $end
#0
$dumpvars
bx B
bx A
bx @
bx ?
bx >
bx =
bx <
bx ;
bx :
bx 9
bx 8
b110x 7
b0xxx 6
b100x 5
bx 4
b10x 3
b1xxx 2
bx 1
bz 0
r0 /
b10 .
b0 -
bx ,
bx +
r0 *
r0 )
0(
0'
0&
0%
bx $
bz #
x"
bx !
$end
#35
1%
#70
b0 A
b0 @
b1100 7
b11 6
b100 3
b1011 2
b1000 5
b111 4
0"
b0 =
b0 <
b0 ;
b0 !
b0 1
b0 :
b0 9
b0 ?
b0 8
b0 >
b0 B
1'
0%
#105
1%
#140
b1 9
1&
b101000010010001 #
b101000010010001 0
b1 +
0%
0'
#175
b100 :
b10 9
b0 B
b1 8
1%
#210
b10 +
b110011111100010 #
b110011111100010 0
0%
#245
b1000 :
b11 9
b10 8
1%
#280
b11 +
b1010000010000011 #
b1010000010000011 0
0%
#315
b1100 :
b100 9
b11 8
1%
#350
b100 +
b110100111010011 #
b110100111010011 0
0%
#385
b1101 7
b1100 2
b0 B
b1 :
b101 9
b100 8
1%
#420
b101 +
b10000111100010 #
b10000111100010 0
0%
#455
b101 :
b110 9
b1001101111010011000000000000000 ;
b0 B
b101 8
1%
#490
b110 +
b1001100011111001 #
b1001100011111001 0
0%
#525
b0 ;
b1001 :
b111 9
b110 8
1%
#560
b111 +
b1100011101001100 #
b1100011101001100 0
0%
#595
b1101 :
b1000 9
b10100110001101100110011001100 =
b1010011000110110011001100110010 <
b111 8
1%
#630
b1000 +
b110000000000 #
b110000000000 0
0%
#665
b1001 5
b1000 4
b0 =
b0 <
b0 B
b10 :
b1001 9
b1000 8
1%
#700
b1001 +
b111010100011111 #
b111010100011111 0
0%
#735
b110 :
b1010 9
b111110111000011000100100000000000000 ;
b0 B
b1001 8
1%
#770
b1010 +
b111011100000010 #
b111011100000010 0
0%
#805
b111111010101011110010000000000000000 ;
b1010 :
b1011 9
b1010 8
1%
#840
b1011 +
b1010100001011010 #
b1010100001011010 0
0%
#875
b1110 :
b1100 9
b111111101100111001110000000000000000 =
b111110110011100111000000000000000000 <
b0 ;
b0 B
b1011 8
1%
#910
b1100 +
b111100001111000 #
b111100001111000 0
0%
#945
b100 6
b101 3
b111111110100101010001100110011001100 =
b111111010010101000110011001100110011 <
b0 B
b11 :
b1101 9
b1100 8
1%
#980
b1101 +
b111010100001000 #
b111010100001000 0
0%
#1015
b111 :
b1110 9
b0 =
b0 <
b1001111010111100100000000000000 ;
b0 B
b1101 8
1%
#1050
b1110 +
b1111110001000010 #
b1111110001000010 0
0%
#1085
b1001000000000000000000000000 ;
b0 B
b1011 :
b1111 9
b1110 8
1%
#1120
b1111 +
b100110011011111 #
b100110011011111 0
0%
#1155
b1111 :
b0 9
b1 ?
b10101001010100011001100110011 =
b1010100101010001100110011001100 <
b1011010010110100000000000000000 ;
b0 B
b1111 8
1%
#1190
b10000 +
b1010010001010011 #
b1010010001010011 0
0%
#1225
b1100 7
b11 6
b100 3
b1011 2
b1000 5
b111 4
b10011001100110011001100110 =
b1001100110011001100110011001 <
b0 ;
b0 B
b0 :
b1 9
b0 8
b1 >
1%
#1260
b1 9
bz #
bz 0
0&
0%
#1295
b11000000101111111111111111111 =
b1100000010111111111111111111111 <
b111100011011001100000000000000 ;
b10011001100110011001100100 B
b100 :
b10 9
b1 8
1%
#1330
0%
#1365
b0 =
b0 <
b11001110111001011001100110010 ;
b10011001100110011001100100 A
b11000000101111111111111111100 B
b1000 :
b11 9
b10 8
1%
#1400
0%
#1435
b10000000111001111111111111111 =
b1000000011100111111111111111111 <
b1100010001101010101100110010011 ;
b11000000101111111111111111100 A
b0 B
b1100 :
b100 9
b11 8
1%
#1470
0%
#1505
b1101 7
b1100 2
b110111001011000010100011110 =
b11011100101100001010001111000 <
b10010010100000000111111111110110 ;
b10000000111001111111111111100 A
b0 B
b1 :
b101 9
b100 8
b0 !
b0 1
1%
#1540
0%
#1575
b11010001100000101110000100111 =
b1101000110000010111000010011100 <
b1110101001100000010111111110110 ;
b110111001011000010100011100 A
b10011001100110011001100100 @
b0 B
b101 :
b110 9
b101 8
1%
#1610
0%
#1645
b100111000100010011001100110000 =
b10011100010001001100110011000000 <
b111111000000110101110000000101000011 ;
b11010001100000101110000100100 A
b11010011111100110011001100000 @
b0 B
b1001 :
b111 9
b110 8
1%
#1680
0%
#1715
b11111010000000000110011001001 =
b1111101000000000011001100100110 <
b1111011010010010010110101101011 ;
b100111000100010011001100110000 A
b11000000101111111111111111100 @
b0 B
b1101 :
b1000 9
b0 !
b0 1
b111 8
1%
#1750
0%
#1785
b1001 5
b1000 4
b111111101111001010000100010010011010 =
b111110111100101000010001001001101001 <
b1000001010100000110110011001001 ;
b11111010000000000110011001000 A
b10111000000101000010100011000 @
b0 B
b10 :
b1001 9
b1000 8
1%
#1820
0%
#1855
b100000111000000101000001100000 =
b10000011100000010100000110000001 <
b111111101010101010111000100101101100 ;
b111111110001100011101010101011111100 A
b100001000101011110000101000000 @
b0 B
b110 :
b1010 9
b1001 8
1%
#1890
0%
#1925
b10001011010101100011110101100 =
b1000101101010110001111010110010 <
b111110001101000011000010001101011110 ;
b111000111110000101000001011100 A
b1000001010000011000111101010100 @
b10011001100110011001100100 B
b1010 :
b1011 9
b1010 8
b111110100000000001100110010 !
b111110100000000001100110010 1
1%
#1960
0%
#1995
b111111111010010011111110000001100000 =
b111111101001001111111000000110000011 <
b1010100011010111010100 ;
b10001011010101100011110101100 A
b100111000100010011001100110000 @
b11000000101111111111111111100 B
b1110 :
b1100 9
b0 !
b0 1
b1011 8
1%
#2030
0%
#2065
b100 6
b101 3
b111111100001010110001001000111110110 =
b111110000101011000100100011111011010 <
b111100101011001010110100011100 ;
b1001101010110010101111100 A
b1110011010000101000101100000 @
b10000000111001111111111111100 B
b11 :
b1101 9
b1100 8
1%
#2100
0%
#2135
b10110100000110001101 =
b1011010000011000110111 <
b1000101001000000111101111010001 ;
b111111111011100010001110111000011000 A
b10000000010001001010011111000 @
b110111001011000010100011100 B
b111 :
b1110 9
b111110100000000001100110010 !
b111110100000000001100110010 1
b1101 8
1%
#2170
0%
#2205
b10000001011100000110000000110 =
b1000000101110000011000000011011 <
b111111101101010111110010010110111000 ;
b100111000111000111010010111100 A
b110010010010110001100000001100 @
b11010001100000101110000100100 B
b1011 :
b1111 9
b1110 8
b11111000010101100010010001111101 !
b11111000010101100010010001111101 1
1%
#2240
0%
#2275
b10010011011110000111111110011 =
b1001001101111000011111111001100 <
b10000110000000111111001011000011 ;
b10000001011100000110000000100 A
b10001011010101100011110101100 @
b100111000100010011001100110000 B
b1111 :
b10000 9
b110000001011111111111111111 !
b110000001011111111111111111 1
b1111 8
1%
#2310
0%
#2345
b1100 7
b11 6
b100 3
b1011 2
b1000 5
b111 4
b111111111011000010000100111001010011 =
b111111101100001000010011100101001100 <
b111111010110011010011001011001000000 ;
b11111010000000000110011001000 A
b111111111010010011111110000001100000 @
b10010011011110000111111110000 B
b0 :
b10001 9
b10000 8
b100000001110011111111111111 !
b100000001110011111111111111 1
1%
#2380
0%
#2415
b100011101111001100100101000100 =
b10001110111100110010010100010010 <
b10010010011100111101010110111000 ;
b1100101110101010010001000 A
b111111011011101010000111001001010100 @
b11010010010000101101100011000 B
b100 :
b10010 9
b11111011110010100001000100100110 !
b11111011110010100001000100100110 1
b10001 8
1%
#2450
0%
#2485
b111111110100111010001111010011011101 =
b111111010011101000111101001101110110 <
b1001011000110100110111010000001 ;
b11011111010001001111010110000 A
b111111100001011000111101001110000000 @
b10010111001010000110111011100 B
b1000 :
b10011 9
b10010 8
b101101000001100011 !
b101101000001100011 1
1%
#2520
0%
#2555
b100111000011011101001010010111 =
b10011100001101110100101001011100 <
b11000001110110001110011101110110 ;
b110101001001111001000011110000 A
b10000001110010100110110010000 @
b10101110010010100010100111100 B
b1100 :
b10100 9
b11111101001110100011110100110111 !
b11111101001110100011110100110111 1
b10011 8
1%
#2590
0%
#2625
b1101 7
b1100 2
b10100000001110000110001100110 =
b1010000000111000011000110011001 <
b11001011001010111011011100000010 ;
b100001010111011011001011110100 A
b10010011011110000111111110000 @
b110111001011000010100011100 B
b1 :
b10101 9
b10100 8
b11111011110010100001000100100110 !
b11111011110010100001000100100110 1
1%
#2660
0%
#2695
b110011101100010100111011001001 =
b11001110110001010011101100100110 <
b10001011110010111111101100111010 ;
b111111110101010111111001111001011000 A
b1101011101110101111001000000 @
b10100100000000011110010000100 B
b101 :
b10110 9
b101101000001100011 !
b101101000001100011 1
b10101 8
1%
#2730
0%
#2765
b110110001011011100101001100110 =
b11011000101101110010100110011010 <
b111110001101100001011001001101000111 ;
b110011101111001001000001010100 A
b11110110001010001011110010100 @
b1000011010011100010100100100 B
b1001 :
b10111 9
b10110 8
b11111101001110100011110100110111 !
b11111101001110100011110100110111 1
1%
#2800
0%
#2835
b100101010001110111011000110001 =
b10010101000111011101100011000100 <
b10110110010100110011101000111100 ;
b1000110010110111101011001101000 A
b11000101001011011111000100000 @
b10110100000110001100 B
b1101 :
b11000 9
b111110100000000001100110010 !
b111110100000000001100110010 1
b10111 8
1%
#2870
0%
#2905
b1001 5
b1000 4
b111111100001011110001111010000010010 =
b111110000101111000111101000001001011 <
b10001100111110010000000100000011 ;
b110111101101101000011000100000 A
b111011000101001101111011111000 @
b111111101111001010000100010010011000 B
b10 :
b11001 9
b11000 8
b101101000001100011 !
b101101000001100011 1
1%
#2940
0%
#2975
b110000100111101011101000110001 =
b11000010011110101110100011000110 <
b111111111010100011110011100011110011 ;
b111111011100100000010100001001100000 A
b1000111101110000101101100101100 @
b110011010011110110000001010000 B
b110 :
b11010 9
b11111101001110100011110100110111 !
b11111101001110100011110100110111 1
b11001 8
1%
#3010
0%
#3045
b100101100101111011110000000000 =
b10010110010111101111000000000010 <
b111100110111111000111000110101000111 ;
b1010100010110111000001101110100 A
b1101001110111110001100100101100 @
b1100011100110001010111111100 B
b1010 :
b11011 9
b11010 8
b1001010100011101110110001100 !
b1001010100011101110110001100 1
1%
#3080
0%
#3115
b111111111110100011001001011110111000 =
b111111111010001100100101111011100000 <
b10111000111010010100000111000 ;
b11010100000001011000011011100 A
b110110001011011100101001100100 @
b100011101111001100100101000100 B
b1110 :
b11100 9
b11111000010101100010010001111101 !
b11111000010101100010010001111101 1
b11011 8
1%
#3150
0%
#3185
b100 6
b101 3
b111111001010101000110001010010011011 =
b111100101010100011000101001001101110 <
b1000100000000001101000100100100 ;
b10010100100111010010000011100 A
b110110000000110101001000000 @
b1000011001100110010010001000 B
b11 :
b11101 9
b11100 8
b11111101001110100011110100110111 !
b11111101001110100011110100110111 1
1%
#3220
0%
#3255
b110001010011110100010010111 =
b11000101001111010001001011100 <
b1110110101000001101101101010101 ;
b111111111110010101000110001101100000 A
b10010000101111010111001000000 @
b10100000100100100110111110000 B
b111 :
b11110 9
b1001010100011101110110001100 !
b1001010100011101110110001100 1
b11101 8
1%
#3290
0%
#3325
b10010001000100101100111100111 =
b1001000100010010110011110011101 <
b111111110100010101100111110011001111 ;
b111100010101111011001011111000 A
b1010110001101100111011000110000 @
b1000011110111110101101011001100 B
b1011 :
b11111 9
b11110 8
b11110010101010001100010100100110 !
b11110010101010001100010100100110 1
1%
#3360
0%
#3395
b11111101000100101110010011110 =
b1111110100010010111001001111011 <
b10011001001011000110000001001100 ;
b10010001000100101100111100100 A
b100101100101111011110000000000 @
b110110001011011100101001100100 B
b1111 :
b100000 9
b1000111011110011001001010001 !
b1000111011110011001001010001 1
b11111 8
1%
#3430
0%
#3465
b1100 7
b11 6
b100 3
b1011 2
b1000 5
b111 4
b111111111100111000111101110100000011 =
b111111110011100011110111010000001110 <
b111111000111010011111101110110001110 ;
b100101010001110111011000110000 A
b111111111110100011001001011110111000 @
b11111101000100101110010011100 B
b0 :
b100001 9
b100000 8
b1001110000110111010010100101 !
b1001110000110111010010100101 1
1%
#3500
0%
#3535
b101000110110001010001000110101 =
b10100011011000101000100011010111 <
b10011110110110110011011011000011 ;
b1000110110101000010101100 A
b111111001001001011111010110001010000 @
b100010001010110101001100110000 B
b100 :
b100010 9
b11111000010111100011110100000100 !
b11111000010111100011110100000100 1
b100001 8
1%
#3570
0%
