code/GSIM.v
module GSIM(clk, reset, in_en, b_in, out_valid, x_out);
    input               clk;
    input               reset;
    input               in_en;
    input signed [15:0] b_in;

    output        out_valid;
    output [31:0] x_out;

    localparam RECEIVE = 0;
    localparam CALC    = 1;
    localparam SEND    = 2;

    reg signed [15:0] b   [0:15];               //store offsets b1 b2... b16 16bits each
    reg signed [31:0] ans [0:15];               //store answers x1 x2... x16 32bits each

    reg        [ 1:0] state_r, state_w;
    reg        [ 3:0] cnt_r, cnt_w;             //counter to keep track of the number of iterations
    reg        [ 2:0] cnt_stage_r, cnt_stage_w; //counter to keep track of the number of stages
    reg        [ 6:0] cnt_round_r, cnt_round_w; //counter to keep track of the number of rounds
    reg signed [39:0] w1, w2, w3, w4, w5, w6;
    reg signed [47:0] r1_r, r2_r, r3_r, r4_r, r1_w, r2_w, r3_w, r4_w;

    localparam MAX_ITER  = 15; //maximum number of variables
    localparam MAX_ROUND = 69; //maximum number of iterations
    localparam MAX_STAGE = 4;

    assign out_valid = (state_r == SEND); //output valid when in SEND state
    assign x_out     = ans[cnt_r];        //output the current answer

    function signed [47:0] mul_3;
        input signed [47:0] a;
        begin
            mul_3 = a + (a << 1);
        end
    endfunction

    function signed [47:0] mul_6;
        input signed [47:0] a;
        begin
            mul_6 = mul_3(a) << 1;
        end
    endfunction

    function signed [47:0] mul_13;
        input signed [47:0] a;
        begin
            mul_13 = a + (a << 2) + (a << 3);
        end
    endfunction

    always @(*) begin
        case (cnt_r)
            0: begin
                w1 = 0;
                w2 = 0;
                w3 = 0;
                w4 = ans[1];
                w5 = ans[2];
                w6 = ans[3];
            end
            1: begin
                w1 = ans[0];
                w2 = 0;
                w3 = 0;
                w4 = ans[2];
                w5 = ans[3];
                w6 = ans[4];
            end
            2: begin
                w1 = ans[1];
                w2 = ans[0];
                w3 = 0;
                w4 = ans[3];
                w5 = ans[4];
                w6 = ans[5];
            end
            13: begin
                w1 = ans[12];
                w2 = ans[11];
                w3 = ans[10];
                w4 = ans[14];
                w5 = ans[15];
                w6 = 0;
            end
            14: begin
                w1 = ans[13];
                w2 = ans[12];
                w3 = ans[11];
                w4 = ans[15];
                w5 = 0;
                w6 = 0;
            end
            15: begin
                w1 = ans[14];
                w2 = ans[13];
                w3 = ans[12];
                w4 = 0;
                w5 = 0;
                w6 = 0;
            end
            default: begin
                w1 = ans[cnt_r-1];
                w2 = ans[cnt_r-2];
                w3 = ans[cnt_r-3];
                w4 = ans[cnt_r+1];
                w5 = ans[cnt_r+2];
                w6 = ans[cnt_r+3];
            end
        endcase
    end

    always @(*) begin
        r1_w = r1_r;
        r2_w = r2_r;
        r3_w = r3_r;
        r4_w = r4_r;

        if (state_r == CALC) begin
            case (cnt_stage_r)
                3'd0: begin
                    r1_w = {w3, 8'd0} + {w6, 8'd0} + {{8{b[cnt_r][15]}}, b[cnt_r], 24'd0};
                    r2_w = mul_6({(w2 + w5), 8'd0});
                    r3_w = mul_13({(w1 + w4), 8'd0});
                end
                3'd1: r4_w = r1_r - r2_r + r3_r;
                3'd2: r4_w = r4_r + (r4_r >>> 4);
                3'd3: r4_w = r4_r + (r4_r >>> 8);
                3'd4: r4_w = (r4_r >>> 6) + (r4_r >>> 22) + (r4_r >>> 5) + (r4_r >>> 21);
            endcase
        end
    end

    always @(posedge clk or posedge reset) begin
        if(reset)begin
            r1_r <= 0;
            r2_r <= 0;
            r3_r <= 0;
            r4_r <= 0;
        end
        else begin
            r1_r <= r1_w;
            r2_r <= r2_w;
            r3_r <= r3_w;
            r4_r <= r4_w;
            if (state_r == RECEIVE && in_en) begin
                ans[cnt_r] <= 32'd0;
            end
            else if (state_r == CALC) begin
                if (cnt_stage_r == MAX_STAGE) begin
                    ans[cnt_r] <= r4_w[39:8];
                end
            end
        end
    end

    always @(posedge clk) begin
        if (state_r == RECEIVE && in_en) begin
            b[cnt_r]   <= b_in;
            //ans[cnt_r] <= {32'd0};
        end
    end

    //FSM
    always @(*) begin
        state_w     = state_r;
        cnt_w       = cnt_r;
        cnt_stage_w = cnt_stage_r;
        cnt_round_w = cnt_round_r;

        case (state_r)
            RECEIVE: begin
                if (in_en) begin
                    if (cnt_r == 4'd15) begin
                        state_w = CALC;
                        cnt_w   = 0;
                        cnt_stage_w = 0;
                        cnt_round_w = 0;
                    end
                    else begin
                        cnt_w = cnt_r + 1;
                    end
                end
            end

            CALC: begin
                if (cnt_stage_r == MAX_STAGE) begin
                    cnt_stage_w = 0;
                    if (cnt_r == MAX_ITER) begin
                        cnt_w = 0;
                        if (cnt_round_r == MAX_ROUND) begin
                            state_w     = SEND;
                            cnt_round_w = 0;
                        end
                        else cnt_round_w = cnt_round_r + 1;
                    end
                    else cnt_w = cnt_r + 1;
                end
                else cnt_stage_w = cnt_stage_r + 1;
            end

            SEND: begin
                if (cnt_r == 4'd15) begin
                    state_w = RECEIVE;
                    cnt_w   = 0;
                end
                else begin
                    cnt_w = cnt_r + 1;
                end
            end
        endcase
    end

    always @(posedge clk or posedge reset) begin
        if (reset) begin
            state_r     <= RECEIVE;
            cnt_stage_r <= 0;
            cnt_round_r <= 0;
            cnt_r       <= 0;
        end
        else begin
            state_r     <= state_w;
            cnt_stage_r <= cnt_stage_w;
            cnt_round_r <= cnt_round_w;
            cnt_r       <= cnt_w;
        end
    end
endmodule

code/testfixture1.v
`timescale 1ns/10ps
`define CYCLE    1           	         // Modify your clock period here
`define SDFFILE  "./Netlist/GSIM_syn.sdf"	      // Modify your sdf file name
`define PAT      "./pattern1.dat"    
module test;
parameter N_PAT   = 16;
integer k;
reg   clk ;
reg   reset ;
reg   in_en;
reg   [15:0]  b_in;
wire  out_valid;
wire  [31:0]  x_out;

reg   [15:0]  pat_mem   [0:N_PAT-1];
reg   [31:0]  x         [0:N_PAT-1];
reg   [15:0]  b         [0:N_PAT-1];
reg   [15:0]  b_tmp;
integer       loop, i, j, out_f;
reg           stop;
real  Mb [0:15];
real  x_f[0:15];
real  SquareError, error, temp;


   GSIM GSIM( .clk(clk), .reset(reset), .in_en(in_en), .b_in(b_in),
              .out_valid(out_valid), .x_out(x_out));
   

`ifdef SDF
   initial $sdf_annotate(`SDFFILE, GSIM);
`endif

initial	$readmemh (`PAT, pat_mem);


initial begin
   clk         = 1'b0;
   reset       = 1'b0;
   in_en       = 1'b0;
   b_in        = 'hz;
   stop        = 1'b0;
   loop        = 0;
end

always begin #(`CYCLE/2.0) clk = ~clk; end

initial begin
$dumpfile("GSIM.vcd");
$dumpvars;
//$fsdbDumpfile("GSIM.fsdb");
//$fsdbDumpvars;

   out_f = $fopen("out.dat");
   if (out_f == 0) begin
        $display("Output file open error !");
        $finish;
   end
end


initial begin
   @(negedge clk)    reset = 1'b1;
   #`CYCLE                reset = 1'b0;
   
   @(negedge clk)  i=0;
    while (i < N_PAT) begin               
         b_in  = pat_mem[i];
         b[i]  = pat_mem[i];
         in_en = 1'b1;
         i=i+1;                  
      @(negedge clk); 
    end     
    in_en = 1'b0;  b_in=16'hz;
end


always @(negedge clk)begin
   if(loop <16)begin
      if(out_valid)begin
         x[loop]=x_out;
         loop=loop+1;
      end
   end
   else begin
         stop=1;
   end
end


initial begin
   @(posedge stop) 
     for (j=0;j<=15;j=j+1)begin
        if(x[j][31]==1) begin   x_f[j]=~x[j] +1'b1;    x_f[j] =-x_f[j]/65536;  end
        else            begin   x_f[j]= x[j];          x_f[j] = x_f[j]/65536;  end
     end
                          
     Mb[0 ]= 20*x_f[0 ]-13*x_f[1 ]+ 6*x_f[2 ]-   x_f[3 ];
     Mb[1 ]=-13*x_f[0 ]+20*x_f[1 ]-13*x_f[2 ]+ 6*x_f[3 ]-   x_f[4 ];
     Mb[2 ]=  6*x_f[0 ]-13*x_f[1 ]+20*x_f[2 ]-13*x_f[3 ]+ 6*x_f[4 ]-  x_f[5 ];      
     Mb[3 ]=   -x_f[0 ]+ 6*x_f[1 ]-13*x_f[2 ]+20*x_f[3 ]-13*x_f[4 ]+6*x_f[5 ]-x_f[6 ];      
     Mb[4 ]=   -x_f[1 ]+ 6*x_f[2 ]-13*x_f[3 ]+20*x_f[4 ]-13*x_f[5 ]+6*x_f[6 ]-x_f[7 ];
     Mb[5 ]=   -x_f[2 ]+ 6*x_f[3 ]-13*x_f[4 ]+20*x_f[5 ]-13*x_f[6 ]+6*x_f[7 ]-x_f[8 ];                    
     Mb[6 ]=   -x_f[3 ]+ 6*x_f[4 ]-13*x_f[5 ]+20*x_f[6 ]-13*x_f[7 ]+6*x_f[8 ]-x_f[9 ];
     Mb[7 ]=   -x_f[4 ]+ 6*x_f[5 ]-13*x_f[6 ]+20*x_f[7 ]-13*x_f[8 ]+6*x_f[9 ]-x_f[10];
     Mb[8 ]=   -x_f[5 ]+ 6*x_f[6 ]-13*x_f[7 ]+20*x_f[8 ]-13*x_f[9 ]+6*x_f[10]-x_f[11];
     Mb[9 ]=   -x_f[6 ]+ 6*x_f[7 ]-13*x_f[8 ]+20*x_f[9 ]-13*x_f[10]+6*x_f[11]-x_f[12];
     Mb[10]=   -x_f[7 ]+ 6*x_f[8 ]-13*x_f[9 ]+20*x_f[10]-13*x_f[11]+6*x_f[12]-x_f[13];
     Mb[11]=   -x_f[8 ]+ 6*x_f[9 ]-13*x_f[10]+20*x_f[11]-13*x_f[12]+6*x_f[13]-x_f[14];
     Mb[12]=   -x_f[9 ]+ 6*x_f[10]-13*x_f[11]+20*x_f[12]-13*x_f[13]+6*x_f[14]-x_f[15];     
     Mb[13]=   -x_f[10]+ 6*x_f[11]-13*x_f[12]+20*x_f[13]-13*x_f[14]+6*x_f[15];
     Mb[14]=   -x_f[11]+ 6*x_f[12]-13*x_f[13]+20*x_f[14]-13*x_f[15];
     Mb[15]=   -x_f[12]+ 6*x_f[13]-13*x_f[14]+20*x_f[15];   
        
     SquareError = 0;        
     
     for(j=0; j<=15; j=j+1)begin     	  
       	if(b[j][15]==1)begin 
       		b_tmp= ~b[j]+1;
       		temp = b_tmp;
       		error= temp + Mb[j];
       	end
       	else begin
       		error = Mb[j] - b[j];
       	end
       	//$display(" Loop=%d    error= %.15f  \n", j, error);
     	  SquareError = SquareError + error*error;
     end
                   
     $display("-----------------------------------------------------\n");
     $display("            Your Output              Golden X\n");
     $display("  X1:     %.10f            402.1120217501   \n", x_f[0 ]);
     $display("  X2:     %.10f           1689.5336804421   \n", x_f[1 ]);
     $display("  X3:     %.10f           2455.4774264763   \n", x_f[2 ]);
     $display("  X4:     %.10f            563.1671481130   \n", x_f[3 ]);
     $display("  X5:     %.10f            703.0136705772   \n", x_f[4 ]);
     $display("  X6:     %.10f           1745.1919122734   \n", x_f[5 ]);
     $display("  X7:     %.10f             33.2002351074   \n", x_f[6 ]);
     $display("  X8:     %.10f            607.1379155812   \n", x_f[7 ]);
     $display("  X9:     %.10f           -477.5895727426   \n", x_f[8 ]);
     $display(" X10:     %.10f            869.0943789319   \n", x_f[9 ]);
     $display(" X11:     %.10f           1907.5237775384   \n", x_f[10]);
     $display(" X12:     %.10f           1524.3408800767   \n", x_f[11]);
     $display(" X13:     %.10f            596.4154551345   \n", x_f[12]);
     $display(" X14:     %.10f           1476.6345624265   \n", x_f[13]);
     $display(" X15:     %.10f           1011.5707976786   \n", x_f[14]);
     $display(" X16:     %.10f          -1330.8985774801   \n", x_f[15]);          
     $display("-----------------------------------------------------\n");
     $display("So Your Error Ratio=  %.15f\n", SquareError);
     $display("-----------------------------------------------------\n");   
     
     error=SquareError;
     if(error<0.000001 && error!='hx && error!='hz)begin                           
         $display("Your Score Level: A \n");  
         $display("Congratulations! GSIM's Function Successfully!\n");
         $display("-------------------------PASS------------------------\n");
     end    
         
     else if(error>=0.000001 && error <0.000005 && error!='hx && error!='hz)begin
        $display("Your Score Level: B \n");
        $display("Congratulations! GSIM's Function Successfully!\n");
        $display("-------------------------PASS------------------------\n");
     end
     else if(error>=0.000005 && error <0.000010 && error!='hx && error!='hz)begin
        $display("Your Score Level: C \n");
        $display("Congratulations! GSIM's Function Successfully!\n");
        $display("-------------------------PASS------------------------\n");
     end 
     else if(error>=0.000010 && error <0.000050 && error!='hx && error!='hz)begin
        $display("Your Score Level: D \n");
        $display("Congratulations! GSIM's Function Successfully!\n");
        $display("-------------------------PASS------------------------\n");
     end 
        
     else if(error>=0.000050 && error <0.000100 && error!='hx && error!='hz)begin
        $display("Your Score Level: E \n");
        $display("Congratulations! GSIM's Function Successfully!\n");
        $display("-------------------------PASS------------------------\n");
     end     
     else if(error>=0.000100 && error <0.001000 && error!='hx && error!='hz)begin
        $display("Your Score Level: F \n");
        $display("Congratulations! GSIM's Function Successfully!\n");
        $display("-------------------------PASS------------------------\n");
     end 
     else if(error>=0.001000 && error <0.005000 && error!='hx && error!='hz)begin
        $display("Your Score Level: G \n");
        $display("Congratulations! GSIM's Function Successfully!\n");
        $display("-------------------------PASS------------------------\n");
     end 
     else if(error>=0.005000 && error <0.010000 && error!='hx && error!='hz)begin
        $display("Your Score Level: H \n");
        $display("Congratulations! GSIM's Function Successfully!\n");
        $display("-------------------------PASS------------------------\n");
     end 
     else if(error>=0.010000 && error <0.100000 && error!='hx && error!='hz)begin
        $display("Your Score Level: I \n");
        $display("Congratulations! GSIM's Function Successfully!\n");
        $display("-------------------------PASS------------------------\n");
     end 
     else if(error>=0.100000 && error <0.300000 && error!='hx && error!='hz)begin
        $display("Your Score Level: J \n");
        $display("Congratulations! GSIM's Function Successfully!\n");
        $display("-------------------------PASS------------------------\n");
     end 
     else begin
        $display("Your Score Level: K \n");                  
        $display("-------------   GSIM's Function Fail   -------------\n");
        $display("-------------------------Fail------------------------\n");
     end
      
      #(`CYCLE/2); $finish;
                       
end
   
endmodule

code/GSIM.vcd
$date
	Thu May  1 00:37:05 2025
$end
$version
	Icarus Verilog
$end
$timescale
	10ps
$end
$scope module test $end
$var wire 32 ! x_out [31:0] $end
$var wire 1 " out_valid $end
$var reg 16 # b_in [15:0] $end
$var reg 16 $ b_tmp [15:0] $end
$var reg 1 % clk $end
$var reg 1 & in_en $end
$var reg 1 ' reset $end
$var reg 1 ( stop $end
$var real 1 ) SquareError $end
$var real 1 * error $end
$var integer 32 + i [31:0] $end
$var integer 32 , j [31:0] $end
$var integer 32 - loop [31:0] $end
$var integer 32 . out_f [31:0] $end
$var real 1 / temp $end
$scope module GSIM $end
$var wire 16 0 b_in [15:0] $end
$var wire 1 % clk $end
$var wire 1 & in_en $end
$var wire 1 ' reset $end
$var wire 32 1 x_out [31:0] $end
$var wire 1 " out_valid $end
$var reg 4 2 cnt_r [3:0] $end
$var reg 7 3 cnt_round_r [6:0] $end
$var reg 7 4 cnt_round_w [6:0] $end
$var reg 3 5 cnt_stage_r [2:0] $end
$var reg 3 6 cnt_stage_w [2:0] $end
$var reg 4 7 cnt_w [3:0] $end
$var reg 48 8 r1_r [47:0] $end
$var reg 48 9 r1_w [47:0] $end
$var reg 48 : r2_r [47:0] $end
$var reg 48 ; r2_w [47:0] $end
$var reg 48 < r3_r [47:0] $end
$var reg 48 = r3_w [47:0] $end
$var reg 48 > r4_r [47:0] $end
$var reg 48 ? r4_w [47:0] $end
$var reg 2 @ state_r [1:0] $end
$var reg 2 A state_w [1:0] $end
$var reg 40 B w1 [39:0] $end
$var reg 40 C w2 [39:0] $end
$var reg 40 D w3 [39:0] $end
$var reg 40 E w4 [39:0] $end
$var reg 40 F w5 [39:0] $end
$var reg 40 G w6 [39:0] $end
$scope function mul_13 $end
$var reg 48 H a [47:0] $end
$upscope $end
$scope function mul_3 $end
$var reg 48 I a [47:0] $end
$upscope $end
$scope function mul_6 $end
$var reg 48 J a [47:0] $end
$upscope $end
$upscope $end
$upscope $end
$enddefinitions $end
#0
$dumpvars
bx J
bx I
bx H
bx G
bx F
bx E
bx D
bx C
bx B
bx A
bx @
bx ?
bx >
bx =
bx <
bx ;
bx :
bx 9
bx 8
bx 7
bx 6
bx 5
bx 4
bx 3
bx 2
bx 1
bz 0
r0 /
b10 .
b0 -
bx ,
bx +
r0 *
r0 )
0(
0'
0&
0%
bx $
bz #
x"
bx !
$end
#500
1%
#1000
b0 D
b0 C
b0 B
b0 4
b0 6
b0 7
b0 A
b0 ?
b0 =
b0 ;
b0 9
b0 2
b0 3
b0 5
0"
b0 @
b0 >
b0 <
b0 :
b0 8
1'
0%
#1500
1%
#2000
b1 7
1&
b101000010010001 #
b101000010010001 0
b1 +
0%
0'
#2500
b10 7
b1 2
bx !
bx 1
1%
#3000
b10 +
b110011111100010 #
b110011111100010 0
0%
#3500
b11 7
b10 2
1%
#4000
b11 +
b1010000010000011 #
b1010000010000011 0
0%
#4500
b100 7
b11 2
bx !
bx 1
1%
#5000
b100 +
b110100111010011 #
b110100111010011 0
0%
#5500
b101 7
b100 2
1%
#6000
b101 +
b10000111100010 #
b10000111100010 0
0%
#6500
b110 7
b101 2
bx !
bx 1
1%
#7000
b110 +
b1001100011111001 #
b1001100011111001 0
0%
#7500
b111 7
b110 2
1%
#8000
b111 +
b1100011101001100 #
b1100011101001100 0
0%
#8500
b1000 7
b111 2
bx !
bx 1
1%
#9000
b1000 +
b110000000000 #
b110000000000 0
0%
#9500
b1001 7
b1000 2
1%
#10000
b1001 +
b111010100011111 #
b111010100011111 0
0%
#10500
b1010 7
b1001 2
bx !
bx 1
1%
#11000
b1010 +
b111011100000010 #
b111011100000010 0
0%
#11500
b1011 7
b1010 2
1%
#12000
b1011 +
b1010100001011010 #
b1010100001011010 0
0%
#12500
b1100 7
b1011 2
bx !
bx 1
1%
#13000
b1100 +
b111100001111000 #
b111100001111000 0
0%
#13500
b1101 7
b1100 2
1%
#14000
b1101 +
b111010100001000 #
b111010100001000 0
0%
#14500
b1110 7
b0 G
b1101 2
bx !
bx 1
1%
#15000
b1110 +
b1111110001000010 #
b1111110001000010 0
0%
#15500
b1111 7
b0 F
b1110 2
1%
#16000
b1111 +
b100110011011111 #
b100110011011111 0
0%
#16500
b0 7
b1 A
b0 E
b1111 2
bx !
bx 1
1%
#17000
b10000 +
b1010010001010011 #
b1010010001010011 0
0%
#17500
b1 6
b0 H
b0 I
b0 J
b101000010010001000000000000000000000000 9
b0 !
b0 1
b0 2
b1 @
1%
#18000
b1 6
bz #
bz 0
0&
0%
#18500
b10 6
b101000010010001000000000000000000000000 ?
b1 5
b101000010010001000000000000000000000000 8
1%
#19000
0%
#19500
b11 6
b101010110011010000100000000000000000000 ?
b101000010010001000000000000000000000000 >
b10 5
1%
#20000
0%
#20500
b100 6
b101010111101111101010100001000000000000 ?
b11 5
b101010110011010000100000000000000000000 >
1%
#21000
0%
#21500
b1 7
b0 6
b10000000111001111111111111111111011 ?
b101010111101111101010100001000000000000 >
b100 5
1%
#22000
0%
#22500
b11010001011110001111111111001100000000 =
b10000000111001111111111111100000000 H
b1 6
b100000001110011111111111111 B
b110011111100010000000000000000000000000 9
b1 2
b0 5
b0 !
b0 1
b10000000111001111111111111111111011 >
1%
#23000
0%
#23500
b10 6
b1001110001000000001111111111001100000000 ?
b11010001011110001111111111001100000000 <
b110011111100010000000000000000000000000 8
b1 5
1%
#24000
0%
#24500
b11 6
b1010011000000100010000111111001000110000 ?
b10 5
b1001110001000000001111111111001100000000 >
1%
#25000
0%
#25500
b100 6
b1010011010101010010010000011011000100010 ?
b1010011000000100010000111111001000110000 >
b11 5
1%
#26000
0%
#26500
b10 7
b0 6
b11111010000000000110011001010000100 ?
b100 5
b1010011010101010010010000011011000100010 >
1%
#27000
0%
#27500
b110010110010000001010011000101000000000 =
b11111010000000000110011001000000000 H
b1100000101011011111111111101000000000 ;
b10000000111001111111111111100000000 I
b10000000111001111111111111100000000 J
b100000001110011111111111111 C
b111110100000000001100110010 B
b1 6
b111111111010000010000011000000000000000000000000 9
b11111010000000000110011001010000100 >
b10 2
b0 5
1%
#28000
0%
#28500
b10 6
b111111111110110111100111101010011001000000000000 ?
b1 5
b110010110010000001010011000101000000000 <
b1100000101011011111111111101000000000 :
b111111111010000010000011000000000000000000000000 8
1%
#29000
0%
#29500
b11 6
b111111111110110011000110001001000010100100000000 ?
b111111111110110111100111101010011001000000000000 >
b10 5
1%
#30000
0%
#30500
b100 6
b111111111110110010110010111010100100110100101001 ?
b11 5
b111111111110110011000110001001000010100100000000 >
1%
#31000
0%
#31500
b11 7
b0 6
b111111111111111100011000011000100001001111111111 ?
b111111111110110010110010111010100100110100101001 >
b100 5
1%
#32000
0%
#32500
b111111111111010000111100111110101111011100000000 =
b111111111111111100011000011000100001001100000000 H
b10111011100000000100110010110000000000 ;
b11111010000000000110011001000000000 I
b11111010000000000110011001000000000 J
b1 6
b100000001110011111111111111 D
b111110100000000001100110010 C
b1111111111111111000110000110001000010011 B
b110110111011010001111111111111100000000 9
b11 2
b0 5
b0 !
b0 1
b111111111111111100011000011000100001001111111111 >
1%
#33000
0%
#33500
b10 6
b11001100110111001001111100101000000000 ?
b111111111111010000111100111110101111011100000000 <
b10111011100000000100110010110000000000 :
b110110111011010001111111111111100000000 8
b1 5
1%
#34000
0%
#34500
b11 6
b11011001101010100110100100011010100000 ?
b10 5
b11001100110111001001111100101000000000 >
1%
#35000
0%
#35500
b100 6
b11011010100001000001001110000011100110 ?
b11011001101010100110100100011010100000 >
b11 5
1%
#36000
0%
#36500
b100 7
b0 6
b1010001111100011101100101000010110 ?
b100 5
b11011010100001000001001110000011100110 >
1%
#37000
0%
#37500
b10000101001010010000000100001000000000 =
b1010001111100011101100101000000000 H
b111111111111101010010010010011000111001000000000 ;
b111111111111111100011000011000100001001100000000 I
b111111111111111100011000011000100001001100000000 J
b111110100000000001100110010 D
b1111111111111111000110000110001000010011 C
b10100011111000111011001010 B
b1 6
b10100110110010000000110011001000000000 9
b1010001111100011101100101000010110 >
b100 2
b0 5
1%
#38000
0%
#38500
b10 6
b101000001101001111101110000001000000000 ?
b1 5
b10000101001010010000000100001000000000 <
b111111111111101010010010010011000111001000000000 :
b10100110110010000000110011001000000000 8
1%
#39000
0%
#39500
b11 6
b101010101110000100101100111001000100000 ?
b101000001101001111101110000001000000000 >
b10 5
1%
#40000
0%
#40500
b100 6
b101010111000110000001110000100010010010 ?
b11 5
b101010101110000100101100111001000100000 >
1%
#41000
0%
#41500
b101 7
b0 6
b10000000101010011000101100110101110 ?
b101010111000110000001110000100010010010 >
b100 5
1%
#42000
0%
#42500
b11010001000100111000001000010100000000 =
b10000000101010011000101100100000000 H
b111101011101010110001011110000000000 ;
b1010001111100011101100101000000000 I
b1010001111100011101100101000000000 J
b1 6
b1111111111111111000110000110001000010011 D
b10100011111000111011001010 C
b100000001010100110001011001 B
b111111111001100000010001011000100001001100000000 9
b101 2
b0 5
b0 !
b0 1
b10000000101010011000101100110101110 >
1%
#43000
0%
#43500
b10 6
b111111111011110011111000111010011101110000000000 ?
b11010001000100111000001000010100000000 <
b111101011101010110001011110000000000 :
b111111111001100000010001011000100001001100000000 8
b1 5
1%
#44000
0%
#44500
b11 6
b111111111011100011001000011110000111100111000000 ?
b10 5
b111111111011110011111000111010011101110000000000 >
1%
#45000
0%
#45500
b100 6
b111111111011100010000001010000001111001000111001 ?
b111111111011100011001000011110000111100111000000 >
b11 5
1%
#46000
0%
#46500
b110 7
b0 6
b111111111111110010100110000010111011000101101000 ?
b100 5
b111111111011100010000001010000001111001000111001 >
1%
#47000
0%
#47500
b111111111101010001101110100101111111110100000000 =
b111111111111110010100110000010111011000100000000 H
b1100000011111110010100001011000000000 ;
b10000000101010011000101100100000000 I
b10000000101010011000101100100000000 J
b10100011111000111011001010 D
b100000001010100110001011001 C
b1111111111111100101001100000101110110001 B
b1 6
b111111111100100111011011100011101100101000000000 9
b111111111111110010100110000010111011000101101000 >
b110 2
b0 5
1%
#48000
0%
#48500
b10 6
b111111111000011000101010010111001011000100000000 ?
b1 5
b111111111101010001101110100101111111110100000000 <
b1100000011111110010100001011000000000 :
b111111111100100111011011100011101100101000000000 8
1%
#49000
0%
#49500
b11 6
b111111110111111010001101000000100111110000010000 ?
b111111111000011000101010010111001011000100000000 >
b10 5
1%
#50000
0%
#50500
b100 6
b111111110111111000001011100011110111111010001100 ?
b11 5
b111111110111111010001101000000100111110000010000 >
1%
#51000
0%
#51500
b111 7
b0 6
b111111111111100111101000100001001010001001111000 ?
b111111110111111000001011100011110111111010001100 >
b100 5
1%
#52000
0%
#52500
b111111111011000011001110101111000011101000000000 =
b111111111111100111101000100001001010001000000000 H
b111111111110101111100100010001100010011000000000 ;
b111111111111110010100110000010111011000100000000 I
b111111111111110010100110000010111011000100000000 J
b1 6
b100000001010100110001011001 D
b1111111111111100101001100000101110110001 C
b1111111111111001111010001000010010100010 B
b1000000000101010011000101100100000000 9
b111 2
b0 5
b0 !
b0 1
b111111111111100111101000100001001010001001111000 >
1%
#53000
0%
#53500
b10 6
b111111111101010011101111110000100110110100000000 ?
b111111111011000011001110101111000011101000000000 <
b111111111110101111100100010001100010011000000000 :
b1000000000101010011000101100100000000 8
b1 5
1%
#54000
0%
#54500
b11 6
b111111111101001000111110101111101001001111010000 ?
b10 5
b111111111101010011101111110000100110110100000000 >
1%
#55000
0%
#55500
b100 6
b111111111101001000010000111111010101001001100011 ?
b111111111101001000111110101111101001001111010000 >
b11 5
1%
#56000
0%
#56500
b1000 7
b0 6
b111111111111110111011000110010011011100010100110 ?
b100 5
b111111111101001000010000111111010101001001100011 >
1%
#57000
0%
#57500
b111111111110010000000010001111100101100000000000 =
b111111111111110111011000110010011011100000000000 H
b111111111101101101110011000110111100110000000000 ;
b111111111111100111101000100001001010001000000000 I
b111111111111100111101000100001001010001000000000 J
b1111111111111100101001100000101110110001 D
b1111111111111001111010001000010010100010 C
b1111111111111101110110001100100110111000 B
b1 6
b111000111000101000010111011000100000000 9
b111111111111110111011000110010011011100010100110 >
b1000 2
b0 5
1%
#58000
0%
#58500
b10 6
b111101001010100001011100011110100000000 ?
b1 5
b111111111110010000000010001111100101100000000000 <
b111111111101101101110011000110111100110000000000 :
b111000111000101000010111011000100000000 8
1%
#59000
0%
#59500
b11 6
b1000000111111001011100010010000011010000 ?
b111101001010100001011100011110100000000 >
b10 5
1%
#60000
0%
#60500
b100 6
b1000001001111011011010101001000111110000 ?
b11 5
b1000000111111001011100010010000011010000 >
1%
#61000
0%
#61500
b1001 7
b0 6
b11000011101110011110001110010011110 ?
b1000001001111011011010101001000111110000 >
b100 5
1%
#62000
0%
#62500
b100111110000011100001000110110000000000 =
b11000011101110011110001110000000000 H
b111111111111001100010100101110100101000000000000 ;
b111111111111110111011000110010011011100000000000 I
b111111111111110111011000110010011011100000000000 J
b1 6
b1111111111111001111010001000010010100010 D
b1111111111111101110110001100100110111000 C
b110000111011100111100011100 B
b111000011101010100001001010001000000000 9
b1001 2
b0 5
b0 !
b0 1
b11000011101110011110001110010011110 >
1%
#63000
0%
#63500
b10 6
b1100110101011001010011101011111000000000 ?
b100111110000011100001000110110000000000 <
b111111111111001100010100101110100101000000000000 :
b111000011101010100001001010001000000000 8
b1 5
1%
#64000
0%
#64500
b11 6
b1101101000101110111000111010100111100000 ?
b10 5
b1100110101011001010011101011111000000000 >
1%
#65000
0%
#65500
b100 6
b1101101100001001000100101000110110001001 ?
b1101101000101110111000111010100111100000 >
b11 5
1%
#66000
0%
#66500
b1010 7
b0 6
b101001000100011101110010001100001110 ?
b100 5
b1101101100001001000100101000110110001001 >
1%
#67000
0%
#67500
b1000010101111010000011001100011100000000 =
b101001000100011101110010001100000000 H
b10010010110010110110101010100000000000 ;
b11000011101110011110001110000000000 I
b11000011101110011110001110000000000 J
b1111111111111101110110001100100110111000 D
b110000111011100111100011100 C
b1010010001000111011100100011 B
b1 6
b111111111010011000110010110010011011100000000000 9
b101001000100011101110010001100001110 >
b1010 2
b0 5
1%
#68000
0%
#68500
b10 6
b11011111001111110111101011100000000 ?
b1 5
b1000010101111010000011001100011100000000 <
b10010010110010110110101010100000000000 :
b111111111010011000110010110010011011100000000000 8
1%
#69000
0%
#69500
b11 6
b11101101001100110111001010001110000 ?
b11011111001111110111101011100000000 >
b10 5
1%
#70000
0%
#70500
b100 6
b11101110001000001010011000000000100 ?
b11 5
b11101101001100110111001010001110000 >
1%
#71000
0%
#71500
b1011 7
b0 6
b1011001010011001001011110001100 ?
b11101110001000001010011000000000100 >
b100 5
1%
#72000
0%
#72500
b10010001000111000111010101100000000 =
b1011001010011001001011100000000 H
b11110110011010110010101101001000000000 ;
b101001000100011101110010001100000000 I
b101001000100011101110010001100000000 J
b1 6
b110000111011100111100011100 D
b1010010001000111011100100011 C
b10110010100110010010111 B
b111111010010101110011110001110000000000 9
b1011 2
b0 5
b0 !
b0 1
b1011001010011001001011110001100 >
1%
#73000
0%
#73500
b10 6
b100010110000011111001111111010100000000 ?
b10010001000111000111010101100000000 <
b11110110011010110010101101001000000000 :
b111111010010101110011110001110000000000 8
b1 5
1%
#74000
0%
#74500
b11 6
b100100111011100001001100111010001010000 ?
b10 5
b100010110000011111001111111010100000000 >
1%
#75000
0%
#75500
b100 6
b100101000100110000000101001101011000100 ?
b100100111011100001001100111010001010000 >
b11 5
1%
#76000
0%
#76500
b1100 7
b0 6
b1101111001110010111001100100001001 ?
b100 5
b100101000100110000000101001101011000100 >
1%
#77000
0%
#77500
b10110100101111010101101100010100000000 =
b1101111001110010111001100100000000 H
b1000010111110010111000101000000000 ;
b1011001010011001001011100000000 I
b1011001010011001001011100000000 J
b1010010001000111011100100011 D
b10110010100110010010111 C
b11011110011100101110011001 B
b1 6
b111111101001100011101110010001100000000 9
b1101111001110010111001100100001001 >
b1100 2
b0 5
1%
#78000
0%
#78500
b10 6
b1010101001100100000000100101111000000000 ?
b1 5
b10110100101111010101101100010100000000 <
b1000010111110010111000101000000000 :
b111111101001100011101110010001100000000 8
1%
#79000
0%
