code/GSIM.v
module GSIM(clk, reset, in_en, b_in, out_valid, x_out);
    input               clk;
    input               reset;
    input               in_en;
    input signed [15:0] b_in;

    output        out_valid;
    output [31:0] x_out;

    localparam RECEIVE = 0;
    localparam CALC    = 1;
    localparam SEND    = 2;

    reg signed [15:0] b   [0:15];               //store offsets b1 b2... b16 16bits each
    reg signed [47:0] ans [0:15];               //store answers x1 x2... x16 32bits each

    reg        [ 1:0] state_r, state_w;
    reg        [ 3:0] cnt_r, cnt_w;             //counter to keep track of the number of iterations
    reg        [ 2:0] cnt_stage_r, cnt_stage_w; //counter to keep track of the number of stages
    reg        [ 6:0] cnt_round_r, cnt_round_w; //counter to keep track of the number of rounds
    reg signed [47:0] w1, w2, w3, w4, w5, w6;
    reg signed [47:0] r1_r, r2_r, r3_r, r4_r, r1_w, r2_w, r3_w, r4_w;

    localparam MAX_ITER  = 15; //maximum number of variables
    localparam MAX_ROUND = 69; //maximum number of iterations
    localparam MAX_STAGE = 4;

    assign out_valid = (state_r == SEND); //output valid when in SEND state
    assign x_out     = ans[cnt_r][39:8];        //output the current answer

    function signed [47:0] mul_3;
        input signed [47:0] a;
        begin
            mul_3 = a + (a << 1);
        end
    endfunction

    function signed [47:0] mul_6;
        input signed [47:0] a;
        begin
            mul_6 = mul_3(a) << 1;
        end
    endfunction

    function signed [47:0] mul_13;
        input signed [47:0] a;
        begin
            mul_13 = a + (a << 2) + (a << 3);
        end
    endfunction

    always @(*) begin
        case (cnt_r)
            0: begin
                w1 = 0;
                w2 = 0;
                w3 = 0;
                w4 = ans[1];
                w5 = ans[2];
                w6 = ans[3];
            end
            1: begin
                w1 = ans[0];
                w2 = 0;
                w3 = 0;
                w4 = ans[2];
                w5 = ans[3];
                w6 = ans[4];
            end
            2: begin
                w1 = ans[1];
                w2 = ans[0];
                w3 = 0;
                w4 = ans[3];
                w5 = ans[4];
                w6 = ans[5];
            end
            13: begin
                w1 = ans[12];
                w2 = ans[11];
                w3 = ans[10];
                w4 = ans[14];
                w5 = ans[15];
                w6 = 0;
            end
            14: begin
                w1 = ans[13];
                w2 = ans[12];
                w3 = ans[11];
                w4 = ans[15];
                w5 = 0;
                w6 = 0;
            end
            15: begin
                w1 = ans[14];
                w2 = ans[13];
                w3 = ans[12];
                w4 = 0;
                w5 = 0;
                w6 = 0;
            end
            default: begin
                w1 = ans[cnt_r-1];
                w2 = ans[cnt_r-2];
                w3 = ans[cnt_r-3];
                w4 = ans[cnt_r+1];
                w5 = ans[cnt_r+2];
                w6 = ans[cnt_r+3];
            end
        endcase
    end

    always @(*) begin
        r1_w = r1_r;
        r2_w = r2_r;
        r3_w = r3_r;
        r4_w = r4_r;

        if (state_r == CALC) begin
            case (cnt_stage_r)
                3'd0: begin
                    r1_w = w3 + w6 + {{8{b[cnt_r][15]}}, b[cnt_r], 24'd0};
                    r2_w = mul_6((w2 + w5));
                    r3_w = mul_13((w1 + w4));
                end
                3'd1: r4_w = r1_r - r2_r + r3_r;
                3'd2: r4_w = r4_r + (r4_r >>> 4);
                3'd3: r4_w = r4_r + (r4_r >>> 8);
                3'd4: r4_w = (r4_r >>> 6) + (r4_r >>> 22) + (r4_r >>> 5) + (r4_r >>> 21);
            endcase
        end
    end

    always @(posedge clk) begin
        if (state_r == CALC) begin
            r1_r <= r1_w;
            r2_r <= r2_w;
            r3_r <= r3_w;
            r4_r <= r4_w;
            if (cnt_stage_r == MAX_STAGE) begin
                ans[cnt_r] <= r4_w;
            end
        end
    end

    always @(posedge clk) begin
        if (state_r == RECEIVE && in_en) begin
            b[cnt_r]   <= b_in;
            ans[cnt_r] <= {48'd0};
        end
    end

    //FSM
    always @(*) begin
        state_w     = state_r;
        cnt_w       = cnt_r;
        cnt_stage_w = cnt_stage_r;
        cnt_round_w = cnt_round_r;

        case (state_r)
            RECEIVE: begin
                if (in_en) begin
                    if (cnt_r == 4'd15) begin
                        state_w = CALC;
                        cnt_w   = 0;
                        cnt_stage_w = 0;
                        cnt_round_w = 0;
                    end
                    else begin
                        cnt_w = cnt_r + 1;
                    end
                end
            end

            CALC: begin
                if (cnt_stage_r == MAX_STAGE) begin
                    cnt_stage_w = 0;
                    if (cnt_r == MAX_ITER) begin
                        cnt_w = 0;
                        if (cnt_round_r == MAX_ROUND) begin
                            state_w     = SEND;
                            cnt_round_w = 0;
                        end
                        else cnt_round_w = cnt_round_r + 1;
                    end
                    else cnt_w = cnt_r + 1;
                end
                else cnt_stage_w = cnt_stage_r + 1;
            end

            SEND: begin
                if (cnt_r == 4'd15) begin
                    state_w = RECEIVE;
                    cnt_w   = 0;
                end
                else begin
                    cnt_w = cnt_r + 1;
                end
            end
        endcase
    end

    always @(posedge clk or posedge reset) begin
        if (reset) begin
            state_r     <= RECEIVE;
            cnt_stage_r <= 0;
            cnt_round_r <= 0;
            cnt_r       <= 0;
            r1_r        <= 0;
            r2_r        <= 0;
            r3_r        <= 0;
            r4_r        <= 0;
        end
        else begin
            state_r     <= state_w;
            cnt_stage_r <= cnt_stage_w;
            cnt_round_r <= cnt_round_w;
            cnt_r       <= cnt_w;
        end
    end
endmodule

code/testfixture1.v
`timescale 1ns/10ps
`define CYCLE    1           	         // Modify your clock period here
`define SDFFILE  "./Netlist/GSIM_syn.sdf"	      // Modify your sdf file name
`define PAT      "./pattern1.dat"    
module test;
parameter N_PAT   = 16;
integer k;
reg   clk ;
reg   reset ;
reg   in_en;
reg   [15:0]  b_in;
wire  out_valid;
wire  [31:0]  x_out;

reg   [15:0]  pat_mem   [0:N_PAT-1];
reg   [31:0]  x         [0:N_PAT-1];
reg   [15:0]  b         [0:N_PAT-1];
reg   [15:0]  b_tmp;
integer       loop, i, j, out_f;
reg           stop;
real  Mb [0:15];
real  x_f[0:15];
real  SquareError, error, temp;


   GSIM GSIM( .clk(clk), .reset(reset), .in_en(in_en), .b_in(b_in),
              .out_valid(out_valid), .x_out(x_out));
   

`ifdef SDF
   initial $sdf_annotate(`SDFFILE, GSIM);
`endif

initial	$readmemh (`PAT, pat_mem);


initial begin
   clk         = 1'b0;
   reset       = 1'b0;
   in_en       = 1'b0;
   b_in        = 'hz;
   stop        = 1'b0;
   loop        = 0;
end

always begin #(`CYCLE/2.0) clk = ~clk; end

initial begin
$dumpfile("GSIM.vcd");
$dumpvars;
//$fsdbDumpfile("GSIM.fsdb");
//$fsdbDumpvars;

   out_f = $fopen("out.dat");
   if (out_f == 0) begin
        $display("Output file open error !");
        $finish;
   end
end


initial begin
   @(negedge clk)    reset = 1'b1;
   #`CYCLE                reset = 1'b0;
   
   @(negedge clk)  i=0;
    while (i < N_PAT) begin               
         b_in  = pat_mem[i];
         b[i]  = pat_mem[i];
         in_en = 1'b1;
         i=i+1;                  
      @(negedge clk); 
    end     
    in_en = 1'b0;  b_in=16'hz;
end


always @(negedge clk)begin
   if(loop <16)begin
      if(out_valid)begin
         x[loop]=x_out;
         loop=loop+1;
      end
   end
   else begin
         stop=1;
   end
end


initial begin
   @(posedge stop) 
     for (j=0;j<=15;j=j+1)begin
        if(x[j][31]==1) begin   x_f[j]=~x[j] +1'b1;    x_f[j] =-x_f[j]/65536;  end
        else            begin   x_f[j]= x[j];          x_f[j] = x_f[j]/65536;  end
     end
                          
     Mb[0 ]= 20*x_f[0 ]-13*x_f[1 ]+ 6*x_f[2 ]-   x_f[3 ];
     Mb[1 ]=-13*x_f[0 ]+20*x_f[1 ]-13*x_f[2 ]+ 6*x_f[3 ]-   x_f[4 ];
     Mb[2 ]=  6*x_f[0 ]-13*x_f[1 ]+20*x_f[2 ]-13*x_f[3 ]+ 6*x_f[4 ]-  x_f[5 ];      
     Mb[3 ]=   -x_f[0 ]+ 6*x_f[1 ]-13*x_f[2 ]+20*x_f[3 ]-13*x_f[4 ]+6*x_f[5 ]-x_f[6 ];      
     Mb[4 ]=   -x_f[1 ]+ 6*x_f[2 ]-13*x_f[3 ]+20*x_f[4 ]-13*x_f[5 ]+6*x_f[6 ]-x_f[7 ];
     Mb[5 ]=   -x_f[2 ]+ 6*x_f[3 ]-13*x_f[4 ]+20*x_f[5 ]-13*x_f[6 ]+6*x_f[7 ]-x_f[8 ];                    
     Mb[6 ]=   -x_f[3 ]+ 6*x_f[4 ]-13*x_f[5 ]+20*x_f[6 ]-13*x_f[7 ]+6*x_f[8 ]-x_f[9 ];
     Mb[7 ]=   -x_f[4 ]+ 6*x_f[5 ]-13*x_f[6 ]+20*x_f[7 ]-13*x_f[8 ]+6*x_f[9 ]-x_f[10];
     Mb[8 ]=   -x_f[5 ]+ 6*x_f[6 ]-13*x_f[7 ]+20*x_f[8 ]-13*x_f[9 ]+6*x_f[10]-x_f[11];
     Mb[9 ]=   -x_f[6 ]+ 6*x_f[7 ]-13*x_f[8 ]+20*x_f[9 ]-13*x_f[10]+6*x_f[11]-x_f[12];
     Mb[10]=   -x_f[7 ]+ 6*x_f[8 ]-13*x_f[9 ]+20*x_f[10]-13*x_f[11]+6*x_f[12]-x_f[13];
     Mb[11]=   -x_f[8 ]+ 6*x_f[9 ]-13*x_f[10]+20*x_f[11]-13*x_f[12]+6*x_f[13]-x_f[14];
     Mb[12]=   -x_f[9 ]+ 6*x_f[10]-13*x_f[11]+20*x_f[12]-13*x_f[13]+6*x_f[14]-x_f[15];     
     Mb[13]=   -x_f[10]+ 6*x_f[11]-13*x_f[12]+20*x_f[13]-13*x_f[14]+6*x_f[15];
     Mb[14]=   -x_f[11]+ 6*x_f[12]-13*x_f[13]+20*x_f[14]-13*x_f[15];
     Mb[15]=   -x_f[12]+ 6*x_f[13]-13*x_f[14]+20*x_f[15];   
        
     SquareError = 0;        
     
     for(j=0; j<=15; j=j+1)begin     	  
       	if(b[j][15]==1)begin 
       		b_tmp= ~b[j]+1;
       		temp = b_tmp;
       		error= temp + Mb[j];
       	end
       	else begin
       		error = Mb[j] - b[j];
       	end
       	//$display(" Loop=%d    error= %.15f  \n", j, error);
     	  SquareError = SquareError + error*error;
     end
                   
     $display("-----------------------------------------------------\n");
     $display("            Your Output              Golden X\n");
     $display("  X1:     %.10f            402.1120217501   \n", x_f[0 ]);
     $display("  X2:     %.10f           1689.5336804421   \n", x_f[1 ]);
     $display("  X3:     %.10f           2455.4774264763   \n", x_f[2 ]);
     $display("  X4:     %.10f            563.1671481130   \n", x_f[3 ]);
     $display("  X5:     %.10f            703.0136705772   \n", x_f[4 ]);
     $display("  X6:     %.10f           1745.1919122734   \n", x_f[5 ]);
     $display("  X7:     %.10f             33.2002351074   \n", x_f[6 ]);
     $display("  X8:     %.10f            607.1379155812   \n", x_f[7 ]);
     $display("  X9:     %.10f           -477.5895727426   \n", x_f[8 ]);
     $display(" X10:     %.10f            869.0943789319   \n", x_f[9 ]);
     $display(" X11:     %.10f           1907.5237775384   \n", x_f[10]);
     $display(" X12:     %.10f           1524.3408800767   \n", x_f[11]);
     $display(" X13:     %.10f            596.4154551345   \n", x_f[12]);
     $display(" X14:     %.10f           1476.6345624265   \n", x_f[13]);
     $display(" X15:     %.10f           1011.5707976786   \n", x_f[14]);
     $display(" X16:     %.10f          -1330.8985774801   \n", x_f[15]);          
     $display("-----------------------------------------------------\n");
     $display("So Your Error Ratio=  %.15f\n", SquareError);
     $display("-----------------------------------------------------\n");   
     
     error=SquareError;
     if(error<0.000001 && error!='hx && error!='hz)begin                           
         $display("Your Score Level: A \n");  
         $display("Congratulations! GSIM's Function Successfully!\n");
         $display("-------------------------PASS------------------------\n");
     end    
         
     else if(error>=0.000001 && error <0.000005 && error!='hx && error!='hz)begin
        $display("Your Score Level: B \n");
        $display("Congratulations! GSIM's Function Successfully!\n");
        $display("-------------------------PASS------------------------\n");
     end
     else if(error>=0.000005 && error <0.000010 && error!='hx && error!='hz)begin
        $display("Your Score Level: C \n");
        $display("Congratulations! GSIM's Function Successfully!\n");
        $display("-------------------------PASS------------------------\n");
     end 
     else if(error>=0.000010 && error <0.000050 && error!='hx && error!='hz)begin
        $display("Your Score Level: D \n");
        $display("Congratulations! GSIM's Function Successfully!\n");
        $display("-------------------------PASS------------------------\n");
     end 
        
     else if(error>=0.000050 && error <0.000100 && error!='hx && error!='hz)begin
        $display("Your Score Level: E \n");
        $display("Congratulations! GSIM's Function Successfully!\n");
        $display("-------------------------PASS------------------------\n");
     end     
     else if(error>=0.000100 && error <0.001000 && error!='hx && error!='hz)begin
        $display("Your Score Level: F \n");
        $display("Congratulations! GSIM's Function Successfully!\n");
        $display("-------------------------PASS------------------------\n");
     end 
     else if(error>=0.001000 && error <0.005000 && error!='hx && error!='hz)begin
        $display("Your Score Level: G \n");
        $display("Congratulations! GSIM's Function Successfully!\n");
        $display("-------------------------PASS------------------------\n");
     end 
     else if(error>=0.005000 && error <0.010000 && error!='hx && error!='hz)begin
        $display("Your Score Level: H \n");
        $display("Congratulations! GSIM's Function Successfully!\n");
        $display("-------------------------PASS------------------------\n");
     end 
     else if(error>=0.010000 && error <0.100000 && error!='hx && error!='hz)begin
        $display("Your Score Level: I \n");
        $display("Congratulations! GSIM's Function Successfully!\n");
        $display("-------------------------PASS------------------------\n");
     end 
     else if(error>=0.100000 && error <0.300000 && error!='hx && error!='hz)begin
        $display("Your Score Level: J \n");
        $display("Congratulations! GSIM's Function Successfully!\n");
        $display("-------------------------PASS------------------------\n");
     end 
     else begin
        $display("Your Score Level: K \n");                  
        $display("-------------   GSIM's Function Fail   -------------\n");
        $display("-------------------------Fail------------------------\n");
     end
      
      #(`CYCLE/2); $finish;
                       
end
   
endmodule

code/GSIM.vcd
$date
	Wed Apr 30 23:10:11 2025
$end
$version
	Icarus Verilog
$end
$timescale
	10ps
$end
$scope module test $end
$var wire 32 ! x_out [31:0] $end
$var wire 1 " out_valid $end
$var reg 16 # b_in [15:0] $end
$var reg 16 $ b_tmp [15:0] $end
$var reg 1 % clk $end
$var reg 1 & in_en $end
$var reg 1 ' reset $end
$var reg 1 ( stop $end
$var real 1 ) SquareError $end
$var real 1 * error $end
$var integer 32 + i [31:0] $end
$var integer 32 , j [31:0] $end
$var integer 32 - loop [31:0] $end
$var integer 32 . out_f [31:0] $end
$var real 1 / temp $end
$scope module GSIM $end
$var wire 16 0 b_in [15:0] $end
$var wire 1 % clk $end
$var wire 1 & in_en $end
$var wire 1 ' reset $end
$var wire 32 1 x_out [31:0] $end
$var wire 1 " out_valid $end
$var reg 4 2 cnt_r [3:0] $end
$var reg 7 3 cnt_round_r [6:0] $end
$var reg 7 4 cnt_round_w [6:0] $end
$var reg 3 5 cnt_stage_r [2:0] $end
$var reg 3 6 cnt_stage_w [2:0] $end
$var reg 4 7 cnt_w [3:0] $end
$var reg 48 8 r1_r [47:0] $end
$var reg 48 9 r1_w [47:0] $end
$var reg 48 : r2_r [47:0] $end
$var reg 48 ; r2_w [47:0] $end
$var reg 48 < r3_r [47:0] $end
$var reg 48 = r3_w [47:0] $end
$var reg 48 > r4_r [47:0] $end
$var reg 48 ? r4_w [47:0] $end
$var reg 2 @ state_r [1:0] $end
$var reg 2 A state_w [1:0] $end
$var reg 48 B w1 [47:0] $end
$var reg 48 C w2 [47:0] $end
$var reg 48 D w3 [47:0] $end
$var reg 48 E w4 [47:0] $end
$var reg 48 F w5 [47:0] $end
$var reg 48 G w6 [47:0] $end
$scope function mul_13 $end
$var reg 48 H a [47:0] $end
$upscope $end
$scope function mul_3 $end
$var reg 48 I a [47:0] $end
$upscope $end
$scope function mul_6 $end
$var reg 48 J a [47:0] $end
$upscope $end
$upscope $end
$upscope $end
$enddefinitions $end
#0
$dumpvars
bx J
bx I
bx H
bx G
bx F
bx E
bx D
bx C
bx B
bx A
bx @
bx ?
bx >
bx =
bx <
bx ;
bx :
bx 9
bx 8
bx 7
bx 6
bx 5
bx 4
bx 3
bx 2
bx 1
bz 0
r0 /
b10 .
b0 -
bx ,
bx +
r0 *
r0 )
0(
0'
0&
0%
bx $
bz #
x"
bx !
$end
#500
1%
#1000
b0 D
b0 C
b0 B
b0 4
b0 6
b0 7
b0 A
b0 ?
b0 =
b0 ;
b0 9
b0 >
b0 <
b0 :
b0 8
b0 2
b0 3
b0 5
0"
b0 @
1'
0%
#1500
1%
#2000
b1 7
1&
b100111000110100 #
b100111000110100 0
b1 +
0%
0'
#2500
b10 7
b1 2
1%
#3000
b10 +
b1001110100100 #
b1001110100100 0
0%
#3500
b11 7
b10 2
1%
#4000
b11 +
b1010111011010100 #
b1010111011010100 0
0%
#4500
b100 7
b11 2
1%
#5000
b100 +
b1011110101101100 #
b1011110101101100 0
0%
#5500
b101 7
b100 2
1%
#6000
b101 +
b110001011110010 #
b110001011110010 0
0%
#6500
b110 7
b101 2
1%
#7000
b110 +
b1000011101011000 #
b1000011101011000 0
0%
#7500
b111 7
b110 2
1%
#8000
b111 +
b1111110101101010 #
b1111110101101010 0
0%
#8500
b1000 7
b111 2
1%
#9000
b1000 +
b1010101011111110 #
b1010101011111110 0
0%
#9500
b1001 7
b1000 2
1%
#10000
b1001 +
b111101010001010 #
b111101010001010 0
0%
#10500
b1010 7
b1001 2
1%
#11000
b1010 +
b11011001110011 #
b11011001110011 0
0%
#11500
b1011 7
b1010 2
1%
#12000
b1011 +
b11111 #
b11111 0
0%
#12500
b1100 7
b1011 2
1%
#13000
b1100 +
b1111100010011001 #
b1111100010011001 0
0%
#13500
b1101 7
b1100 2
1%
#14000
b1101 +
b1000111101000100 #
b1000111101000100 0
0%
#14500
b1110 7
b0 G
b1101 2
1%
#15000
b1110 +
b10111010010110 #
b10111010010110 0
0%
#15500
b1111 7
b0 F
b1110 2
1%
#16000
b1111 +
b1000101011011101 #
b1000101011011101 0
0%
#16500
b0 7
b1 A
b0 E
b1111 2
1%
#17000
b10000 +
b1001001001001011 #
b1001001001001011 0
0%
#17500
b1 6
b0 !
b0 1
b0 H
b0 I
b0 J
b100111000110100000000000000000000000000 9
b0 2
b1 @
1%
#18000
b1 6
bz #
bz 0
0&
0%
#18500
b10 6
b100111000110100000000000000000000000000 ?
b1 5
b100111000110100000000000000000000000000 8
1%
#19000
0%
#19500
b11 6
b101001100010111010000000000000000000000 ?
b10 5
b100111000110100000000000000000000000000 >
1%
#20000
0%
#20500
b100 6
b101001101101010010101110100000000000000 ?
b11 5
b101001100010111010000000000000000000000 >
1%
#21000
0%
#21500
b1 7
b0 6
b1111101000111111111111111111111011 ?
b100 5
b101001101101010010101110100000000000000 >
1%
#22000
0%
#22500
b11001011010100111111111111111110111111 =
b1111101000111111111111111111111011 H
b1 6
b1111101000111111111111111111111011 B
b1001110100100000000000000000000000000 9
b1 2
b0 5
b1111101000111111111111111111111011 >
1%
#23000
0%
#23500
b10 6
b100011001111000111111111111111110111111 ?
b1 5
b11001011010100111111111111111110111111 <
b1001110100100000000000000000000000000 8
1%
#24000
0%
#24500
b11 6
b100101011100000100011111111111110111010 ?
b10 5
b100011001111000111111111111111110111111 >
1%
#25000
0%
#25500
b100 6
b100101100101011011100001000111110111001 ?
b11 5
b100101011100000100011111111111110111010 >
1%
#26000
0%
#26500
b10 7
b0 6
b1110000110000011001100110011000011 ?
b100 5
b100101100101011011100001000111110111001 >
1%
#27000
0%
#27500
b10110111001110101001100110010111100111 =
b1110000110000011001100110011000011 H
b1011101110101111111111111111111100010 ;
b1111101000111111111111111111111011 I
b1111101000111111111111111111111011 J
b1 6
b1111101000111111111111111111111011 C
b1110000110000011001100110011000011 B
b111111111010111011010100000000000000000000000000 9
b10 2
b0 5
b1110000110000011001100110011000011 >
1%
#28000
0%
#28500
b10 6
b111111111100010100101100101001100110011000000101 ?
b1 5
b10110111001110101001100110010111100111 <
b1011101110101111111111111111111100010 :
b111111111010111011010100000000000000000000000000 8
1%
#29000
0%
#29500
b11 6
b111111111100000101111111011100001100110001100101 ?
b10 5
b111111111100010100101100101001100110011000000101 >
1%
#30000
0%
#30500
b100 6
b111111111100000101000000111100000011110100110001 ?
b11 5
b111111111100000101111111011100001100110001100101 >
1%
#31000
0%
#31500
b11 7
b0 6
b111111111111110100001111000010000101000111100111 ?
b100 5
b111111111100000101000000111100000011110100110001 >
1%
#32000
0%
#32500
b111111111101100111000011011011000010100010111011 =
b111111111111110100001111000010000101000111100111 H
b1010100100100010011001100110010010010 ;
b1110000110000011001100110011000011 I
b1110000110000011001100110011000011 J
b1 6
b1111101000111111111111111111111011 D
b1110000110000011001100110011000011 C
b111111111111110100001111000010000101000111100111 B
b111111111100000101010100111111111111111111111011 9
b11 2
b0 5
b111111111111110100001111000010000101000111100111 >
1%
#33000
0%
#33500
b10 6
b111111111000010111110100000111110101110000100100 ?
b1 5
b111111111101100111000011011011000010100010111011 <
b1010100100100010011001100110010010010 :
b111111111100000101010100111111111111111111111011 8
1%
#34000
0%
#34500
b11 6
b111111110111111001010011011000010101000111100110 ?
b10 5
b111111111000010111110100000111110101110000100100 >
1%
#35000
0%
#35500
b100 6
b111111110111110111010001101101001011001100110111 ?
b11 5
b111111110111111001010011011000010101000111100110 >
1%
#36000
0%
#36500
b100 7
b0 6
b111111111111100111100101110011100101111000111000 ?
b100 5
b111111110111110111010001101101001011001100110111 >
1%
#37000
0%
#37500
b111111111011000010101011011110101100100011011000 =
b111111111111100111100101110011100101111000111000 H
b111111111110111001011010001100011110101101101010 ;
b111111111111110100001111000010000101000111100111 I
b111111111111110100001111000010000101000111100111 J
b1 6
b1110000110000011001100110011000011 D
b111111111111110100001111000010000101000111100111 C
b111111111111100111100101110011100101111000111000 B
b110011001111000000011001100110011000011 9
b100 2
b0 5
b111111111111100111100101110011100101111000111000 >
1%
#38000
0%
#38500
b10 6
b10100011001001010101011010101000110001 ?
b1 5
b111111111011000010101011011110101100100011011000 <
b111111111110111001011010001100011110101101101010 :
b110011001111000000011001100110011000011 8
1%
#39000
0%
#39500
b11 6
b10101101010101111010110000010011010100 ?
b10 5
b10100011001001010101011010101000110001 >
1%
#40000
0%
#40500
b100 6
b10101110000001010000001110111111011000 ?
b11 5
b10101101010101111010110000010011010100 >
1%
#41000
0%
#41500
b101 7
b0 6
b1000001010000100010001010101001100 ?
b100 5
b10101110000001010000001110111111011000 >
1%
#42000
0%
#42500
b1101010000010110111100001010011011100 =
b1000001010000100010001010101001100 H
b111111111101101101100010110101100011010101010000 ;
b111111111111100111100101110011100101111000111000 I
b111111111111100111100101110011100101111000111000 J
b1 6
b111111111111110100001111000010000101000111100111 D
b111111111111100111100101110011100101111000111000 C
b1000001010000100010001010101001100 B
b111111111000010001100111000010000101000111100111 9
b101 2
b0 5
b1000001010000100010001010101001100 >
1%
#43000
0%
#43500
b10 6
b111111111100001110000111000100000011000101110011 ?
b1 5
b1101010000010110111100001010011011100 <
b111111111101101101100010110101100011010101010000 :
b111111111000010001100111000010000101000111100111 8
1%
#44000
0%
#44500
b11 6
b111111111011111110111111100000010011010010001010 ?
b10 5
b111111111100001110000111000100000011000101110011 >
1%
#45000
0%
#45500
b100 6
b111111111011111101111111010000001011010110111110 ?
b11 5
b111111111011111110111111100000010011010010001010 >
1%
#46000
0%
#46500
b110 7
b0 6
b111111111111110011111001111101000000001001111010 ?
b100 5
b111111111011111101111111010000001011010110111110 >
1%
#47000
0%
#47500
b111111111101100010110001011001000010000000110010 =
b111111111111110011111001111101000000001001111010 H
b110000111100011001100111111111001000 ;
b1000001010000100010001010101001100 I
b1000001010000100010001010101001100 J
b1 6
b111111111111100111100101110011100101111000111000 D
b1000001010000100010001010101001100 C
b111111111111110011111001111101000000001001111010 B
b111111111111011101001111110011100101111000111000 9
b110 2
b0 5
b111111111111110011111001111101000000001001111010 >
1%
#48000
0%
#48500
b10 6
b111111111100001111000100110010111111111010100010 ?
b1 5
b111111111101100010110001011001000010000000110010 <
b110000111100011001100111111111001000 :
b111111111111011101001111110011100101111000111000 8
1%
#49000
0%
#49500
b11 6
b111111111100000000000001000110001011111010001100 ?
b10 5
b111111111100001111000100110010111111111010100010 >
1%
#50000
0%
#50500
b100 6
b111111111011111111000001000110011101011101001010 ?
b11 5
b111111111100000000000001000110001011111010001100 >
1%
#51000
0%
#51500
b111 7
b0 6
b111111111111110011111101000010100011001100100011 ?
b100 5
b111111111011111111000001000110011101011101001010 >
1%
#52000
0%
#52500
b111111111101100011011001100001001001100011000111 =
b111111111111110011111101000010100011001100100011 H
b111111111110110111011011101110000000111011011100 ;
b111111111111110011111001111101000000001001111010 I
b111111111111110011111001111101000000001001111010 J
b1 6
b1000001010000100010001010101001100 D
b111111111111110011111001111101000000001001111010 C
b111111111111110011111101000010100011001100100011 B
b111111111010110100001000000100010001010101001100 9
b111 2
b0 5
b111111111111110011111101000010100011001100100011 >
1%
#53000
0%
#53500
b10 6
b111111111001100000000101110111011001111100110111 ?
b1 5
b111111111101100011011001100001001001100011000111 <
b111111111110110111011011101110000000111011011100 :
b111111111010110100001000000100010001010101001100 8
1%
#54000
0%
#54500
b11 6
b111111111001000110000110001110110111100100101010 ?
b10 5
b111111111001100000000101110111011001111100110111 >
1%
#55000
0%
#55500
b100 6
b111111111001000100010111110000011011010010100011 ?
b11 5
b111111111001000110000110001110110111100100101010 >
1%
#56000
0%
#56500
b1000 7
b0 6
b111111111111101011001101000101111110000110010100 ?
b100 5
b111111111001000100010111110000011011010010100011 >
1%
#57000
0%
#57500
b111111111011110001101010001101100111010010000100 =
b111111111111101011001101000101111110000110010100 H
b111111111110110111101110001111010011001011010010 ;
b111111111111110011111101000010100011001100100011 I
b111111111111110011111101000010100011001100100011 J
b1 6
b111111111111110011111001111101000000001001111010 D
b111111111111110011111101000010100011001100100011 C
b111111111111101011001101000101111110000110010100 B
b111011110000011111101000000001001111010 9
b1000 2
b0 5
b111111111111101011001101000101111110000110010100 >
1%
#58000
0%
#58500
b10 6
b100010111111111111011010100010000101100 ?
b1 5
b111111111011110001101010001101100111010010000100 <
b111111111110110111101110001111010011001011010010 :
b111011110000011111101000000001001111010 8
1%
#59000
0%
#59500
b11 6
b100101001011111111011000001100001101110 ?
b10 5
b100010111111111111011010100010000101100 >
1%
#60000
0%
#60500
b100 6
b100101010101010010011000000010010000110 ?
b11 5
b100101001011111111011000001100001101110 >
1%
#61000
0%
#61500
b1001 7
b0 6
b1101111111111111110001000000110001 ?
b100 5
b100101010101010010011000000010010000110 >
1%
#62000
0%
#62500
b10110101111111111100111101001001111101 =
b1101111111111111110001000000110001 H
b111111111110000011001110100011110100100101111000 ;
b111111111111101011001101000101111110000110010100 I
b111111111111101011001101000101111110000110010100 J
b1 6
b111111111111110011111101000010100011001100100011 D
b111111111111101011001101000101111110000110010100 C
b1101111111111111110001000000110001 B
b11001101110000000010100011001100100011 9
b1001 2
b0 5
b1101111111111111110001000000110001 >
1%
#63000
0%
#63500
b10 6
b1000000000100001011011101011110000101000 ?
b1 5
b10110101111111111100111101001001111101 <
b111111111110000011001110100011110100100101111000 :
b11001101110000000010100011001100100011 8
1%
#64000
0%
#64500
b11 6
b1000100000100011100001011010011111101010 ?
b10 5
b1000000000100001011011101011110000101000 >
1%
#65000
0%
#65500
b100 6
b1000100010101011101010010010110110010001 ?
b11 5
b1000100000100011100001011010011111101010 >
1%
#66000
0%
#66500
b1010 7
b0 6
b11001101000000100100101011000101101 ?
b100 5
b1000100010101011101010010010110110010001 >
1%
#67000
0%
#67500
b101001101001000111011100110000001001001 =
b11001101000000100100101011000101101 H
b1010011111111111110100110000100100110 ;
b1101111111111111110001000000110001 I
b1101111111111111110001000000110001 J
b1 6
b111111111111101011001101000101111110000110010100 D
b1101111111111111110001000000110001 C
b11001101000000100100101011000101101 B
b111111111111101011101100000101111110000110010100 9
b1010 2
b0 5
b11001101000000100100101011000101101 >
1%
#68000
0%
#68500
b10 6
b11100100110101000010111110000010110111 ?
b1 5
b101001101001000111011100110000001001001 <
b1010011111111111110100110000100100110 :
b111111111111101011101100000101111110000110010100 8
1%
#69000
0%
#69500
b11 6
b11110011001000010111001001111011000010 ?
b10 5
b11100100110101000010111110000010110111 >
1%
#70000
0%
#70500
b100 6
b11110100000101001001001111101101100000 ?
b11 5
b11110011001000010111001001111011000010 >
1%
#71000
0%
#71500
b1011 7
b0 6
b1011011100010000001001100000000101 ?
b100 5
b11110100000101001001001111101101100000 >
1%
#72000
0%
#72500
b10010100101111010001111011100001000001 =
b1011011100010000001001100000000101 H
b10011001110000011011100000010100001110 ;
b11001101000000100100101011000101101 I
b11001101000000100100101011000101101 J
b1 6
b1101111111111111110001000000110001 D
b11001101000000100100101011000101101 C
b1011011100010000001001100000000101 B
b111111111111110000011000111111110001000000110001 9
b1011 2
b0 5
b1011011100010000001001100000000101 >
1%
#73000
0%
#73500
b10 6
b111111111111101011010111110110001100001101100100 ?
b1 5
b10010100101111010001111011100001000001 <
b10011001110000011011100000010100001110 :
b111111111111110000011000111111110001000000110001 8
1%
#74000
0%
#74500
b11 6
b111111111111101010000101010101100100111110011010 ?
b10 5
b111111111111101011010111110110001100001101100100 >
1%
#75000
0%
#75500
b100 6
b111111111111101001111111110110111010010111101001 ?
b11 5
b111111111111101010000101010101100100111110011010 >
1%
#76000
0%
#76500
b1100 7
b0 6
b111111111111111110111101111111100000100111000011 ?
b100 5
b111111111111101001111111110110111010010111101001 >
1%
#77000
0%
#77500
b111111111111110010100101111001100111111011100111 =
b111111111111111110111101111111100000100111000011 H
b1000100101001100000111001000000011110 ;
b1011011100010000001001100000000101 I
b1011011100010000001001100000000101 J
b1 6
b11001101000000100100101011000101101 D
b1011011100010000001001100000000101 C
b111111111111111110111101111111100000100111000011 B
b111111111001010110101100000100100101011000101101 9
b1100 2
b0 5
b111111111111111110111101111111100000100111000011 >
1%
#78000
0%
#78500
b10 6
b111111111000000100101000011101010100010011110110 ?
b1 5
b111111111111110010100101111001100111111011100111 <
b1000100101001100000111001000000011110 :
b111111111001010110101100000100100101011000101101 8
1%
#79000
0%
